Lab 1/DFlipFlop.v
module DFlipFlop(q, qBar, D, clk, rst);
  input D, clk, rst;
  output q, qBar;
  reg q;
  not n1 (qBar, q);
  always@ (negedge rst or posedge clk) begin
    if(!rst)
      q = 0;
    else
      q = D;
  end
endmodule

module testbench;
  reg clk, D, rst;
  wire q, qBar;
  DFlipFlop myFlipFlop(q, qBar, D, clk, rst);
  parameter ClockDelay = 1;
  initial begin //setup the clock
    clk <= 0;
    forever begin
      #(ClockDelay);
      clk <= ~clk;
    end
  end

  initial begin
    $dumpfile("DFlipFlop.vcd");
    $dumpvars(1,myFlipFlop);
    rst = 1'b0; #10;
    rst = 1'b1; #10;
    D = 1'b1;  #10;
    D = 1'b0; #10;
    $finish;
  end
endmodule

Lab 1/rippleCounter.v
`include "DFlipFlop.v"

module rippleCounter(count, clk, reset);
  input clk, reset;
  output [3:0] count;
  wire [3:0] q, qBar;
  genvar i;
  DFlipFlop zerothFlipFlop(q[0], count[0], count[0], clk, reset); //set up the flip flops
  generate
    for(i = 1; i < 4; i = i + 1) begin : eachFlipFlop
      DFlipFlop nthFlipFlop(q[i], count[i], count[i], q[i - 1], reset);
    end
  endgenerate
endmodule

module rippleCounter_testbench;
  reg clk, rst;
  wire [3:0] count;
  rippleCounter myRippleCounter(count, clk, rst);
  parameter ClockDelay = 1;
  initial begin //setup the clock
    clk <= 0;
    forever begin
      #(ClockDelay);
      clk <= ~clk;
    end
  end
  integer i;
  initial begin
    $dumpfile("rippleCounter.vcd");
    $dumpvars(1, myRippleCounter);
    rst = 1'b0; #ClockDelay;
    rst = 1'b1; #ClockDelay;
    for(i = 0; i < 32; i++) begin
      #ClockDelay; //run 32 clock cycles
    end
    $finish;
  end
endmodule

Lab 1/rippleCounter.vcd
$date
	Tue Jan  9 20:14:25 2018
$end
$version
	Icarus Verilog
$end
$timescale
	1s
$end
$scope module rippleCounter_testbench $end
$scope module myRippleCounter $end
$var wire 1 ! clk $end
$var wire 1 " reset $end
$var wire 4 # q [3:0] $end
$var wire 4 $ count [3:0] $end
$upscope $end
$upscope $end
$enddefinitions $end
#0
$dumpvars
b1111 $
b0 #
0"
0!
$end
#1
b0 $
b1111 #
1!
1"
#2
0!
#3
b1 $
b1110 #
1!
#4
0!
#5
b10 $
b1101 #
1!
#6
0!
#7
b11 $
b1100 #
1!
#8
0!
#9
b100 $
b1011 #
1!
#10
0!
#11
b101 $
b1010 #
1!
#12
0!
#13
b110 $
b1001 #
1!
#14
0!
#15
b111 $
b1000 #
1!
#16
0!
#17
b1000 $
b111 #
1!
#18
0!
#19
b1001 $
b110 #
1!
#20
0!
#21
b1010 $
b101 #
1!
#22
0!
#23
b1011 $
b100 #
1!
#24
0!
#25
b1100 $
b11 #
1!
#26
0!
#27
b1101 $
b10 #
1!
#28
0!
#29
b1110 $
b1 #
1!
#30
0!
#31
b1111 $
b0 #
1!
#32
0!
#33
b0 $
b1111 #
1!
