Lab 2/moveBathysphere.v
//11 is off, 10, is outside, 01 is chamber, 00 is inside
module moveBathysphere (bathysphereState, innerDoorState, outerDoorState, arriving, departing, clk, reset);
  input wire innerDoorState, outerDoorState, arriving, departing, clk, reset;
  output reg [1:0] bathysphereState;
  always @ (posedge clk) begin
    if(arriving ^ departing) begin
        case(bathysphereState)
          2'b11: begin
            if(arriving) begin
              bathysphereState = 2'b10;
            end else begin
              bathysphereState = 2'b00;
            end
          end
          2'b10: begin
            if(arriving && !outerDoorState) begin
              bathysphereState = 2'b01;
            end
            if(departing) begin
              bathysphereState = 2'b11;
            end
          end
          2'b01: begin
            if(arriving && !innerDoorState) begin
              bathysphereState = 2'b00;
            end
            if(departing && !outerDoorState) begin
              bathysphereState = 2'b10;
            end
          end
          2'b00: begin
            if(departing && !innerDoorState) begin
              bathysphereState = 2'b01;
            end
            if(arriving) begin
              bathysphereState = 2'b11;
            end
          end
          default: begin
            bathysphereState = 2'b11;
          end
        endcase
      end else begin
        bathysphereState = 2'b11;
      end
  end
endmodule

/*module moveBathysphere_testbench;
  reg innerDoorState, outerDoorState, arriving, departing, clk, reset;
  wire [1:0] bathysphereState;
  moveBathysphere dut (bathysphereState, innerDoorState, outerDoorState, arriving, departing, clk, reset);
  parameter ClockDelay = 2;
  initial begin //setup the clock
    clk <= 0;
    forever begin
      #(ClockDelay/2);
      clk <= ~clk;
    end
  end
  initial begin //begin testing
    $dumpfile("moveBathysphere.vcd");
    $dumpvars(1,dut);
    innerDoorState = 1'b0;
    outerDoorState = 1'b0;
    arriving = 1'b0;
    departing = 1'b0;
    reset = 1'b0; #ClockDelay;
    reset = 1'b1; #ClockDelay;
    #ClockDelay;
    arriving = 1'b1;
    #ClockDelay;
    departing = 1'b1;
    #ClockDelay;
    arriving = 1'b0;
    #ClockDelay;
    #ClockDelay;
    #ClockDelay;
    innerDoorState = 1'b1;
    #ClockDelay;
    #ClockDelay;
    #ClockDelay;
    innerDoorState = 1'b0;
    outerDoorState = 1'b1;
    #ClockDelay;
    #ClockDelay;
    arriving = 1'b1;
    #ClockDelay;
    outerDoorState = 1'b0;
    departing = 1'b0;
    innerDoorState = 1'b1;
    #ClockDelay;
    #ClockDelay;
    #ClockDelay;
    innerDoorState = 1'b0;
    outerDoorState = 1'b1;
    #ClockDelay;
    #ClockDelay;
    #ClockDelay;
    $finish;
  end
endmodule*/

Lab 2/pressurizer.v
module pressurizer (pressurized, innerDoorState, outerDoorState, pressurizeSignal, depressurizeSignal, reset, clk);
  input wire innerDoorState, outerDoorState, pressurizeSignal, depressurizeSignal, reset, clk;
  output reg pressurized;
  reg[1:0] pressurizeState; //00 means depressurize, 01 means pressurize, 10 means wait
  reg[3:0] count;
  always @ (posedge clk) begin
    case(pressurizeState)
        2'b00: begin
          if(!pressurized) begin
            pressurizeState <= 2'b10;
          end
        end
        2'b01: begin
          if(pressurized) begin
            pressurizeState <= 2'b10;
          end
        end
        2'b10: begin
          if(!pressurizeSignal && !innerDoorState && !outerDoorState && !pressurized) begin
            pressurizeState <= 2'b01;
          end else if(!depressurizeSignal && !innerDoorState && !outerDoorState && pressurized) begin
            pressurizeState <= 2'b00;
          end
        end
        default: begin
          pressurizeState <= 2'b10;
        end
    endcase
  end
  always @ (posedge clk) begin
    if(!reset) begin
      count <= 4'd0;
      pressurized <= 1'b0;
    end else begin
      if(pressurizeState == 2'b01) begin
        if(!outerDoorState && !innerDoorState && !pressurized) begin //can only pressurize if the doors are closed and not already pressurized
          if(count == 4'd7) begin //pressurize the chamber after 7 ticks of the clock
            pressurized <= 1'b1;
            count <= 4'd0;
          end else begin
            count <= count + 1'b1;
          end
        end
      end else if(pressurizeState == 2'b00) begin
        if(!outerDoorState && !innerDoorState && pressurized) begin //can only depressurize if doors are closed and already pressurized
          if(count == 4'd8) begin
            pressurized <= 1'b0;
            count <= 4'd0;
          end else begin
            count <= count + 1'b1;
          end
        end
      end
    end
  end
endmodule

/*module pressurizer_testbench;
  wire pressurized;
  reg clk, reset, pressurizeSignal, depressurizeSignal, innerDoorState, outerDoorState;
  pressurizer dut (pressurized, innerDoorState, outerDoorState, pressurizeSignal, depressurizeSignal, reset, clk);
  parameter ClockDelay = 2;
  initial begin //setup the clock
    clk <= 0;
    forever begin
      #(ClockDelay/2);
      clk <= ~clk;
    end
  end
  integer i;
  initial begin
    $dumpfile("pressurizer.vcd");
    $dumpvars(1,dut);
    reset <= 1'b0; #(2*ClockDelay);
    reset <= 1'b1; #ClockDelay;
    innerDoorState <= 1'b0;
    outerDoorState <= 1'b0;
    depressurizeSignal <= 1'b1;
    pressurizeSignal <= 1'b1;
    #ClockDelay;
    pressurizeSignal <= 1'b0; //begin pressurization
    #ClockDelay;
    pressurizeSignal <= 1'b1;
    for(i = 0; i < 10; i = i + 1)begin
        #ClockDelay;
    end
    #ClockDelay;
    depressurizeSignal <= 1'b0;
    #ClockDelay;
    depressurizeSignal <= 1'b1;
    for(i = 0; i < 8; i = i + 1)begin
      #ClockDelay;
    end
    #ClockDelay;
    pressurizeSignal <= 1'b0; //begin pressurization but inner door is open
    innerDoorState <= 1'b1;
    #ClockDelay;
    pressurizeSignal <= 1'b1;
    #ClockDelay;
    #ClockDelay;
    #ClockDelay;
    depressurizeSignal <= 1'b0; //begin depressurization but inner door is open
    #ClockDelay;
    #ClockDelay;
    depressurizeSignal <= 1'b1;
    #ClockDelay;
    #ClockDelay;
    innerDoorState <= 1'b0;
    depressurizeSignal <= 1'b0;
    #ClockDelay;
    #ClockDelay;
    #ClockDelay;
    depressurizeSignal <= 1'b1;
    #ClockDelay;
    #ClockDelay;
    $finish;
  end
endmodule*/

Lab 2/innerDoor.v
module innerDoor(doorState, commandSwitch, outerDoorState, pressurized, reset, clk);
  input wire commandSwitch, outerDoorState, reset, pressurized, clk;
  output reg doorState;
  always @(posedge clk) begin
    if(!reset) begin
      doorState <= 1'b0; //close the door on reset
    end else begin
      if(commandSwitch) begin //trying to open the inner door
        if(!pressurized && !outerDoorState) begin //can only do it if chamber is not pressurized and outer door is closed
          doorState <= 1'b1;
        end
      end else begin
        doorState <= 1'b0; //close the door
      end
    end
  end
endmodule

module innerDoor_testbench;
  reg clk, reset, commandSwitch, outerDoorState, pressurized;
  wire doorState;
  innerDoor dut (doorState, commandSwitch, outerDoorState, pressurized, reset, clk);
  parameter ClockDelay = 2;
  initial begin //setup the clock
    clk <= 0;
    forever begin
      #(ClockDelay/2);
      clk <= ~clk;
    end
  end
  initial begin //begin testing
    $dumpfile("innerDoor.vcd");
    $dumpvars(1,dut);
    reset = 1'b0; #ClockDelay;
    reset = 1'b1; #ClockDelay;
    commandSwitch = 1'b1;
    pressurized = 1'b1;
    outerDoorState = 1'b0;
    #ClockDelay; //command is sent, but the chamber is pressurized
    pressurized = 1'b0;
    outerDoorState = 1'b1;
    #ClockDelay //command is sent, but outer door is open
    commandSwitch = 1'b0;
    pressurized = 1'b0;
    outerDoorState = 1'b0;
    #ClockDelay //conditions are met, but the command is never sent
    commandSwitch = 1'b1;
    #ClockDelay //conditions are met, and the command is sent
    commandSwitch = 1'b0;
    #ClockDelay //command is back to off


    $finish;
  end
endmodule

Lab 2/outerDoor.v
//1 means open, 0 means closed
module outerDoor(doorState, commandSwitch, innerDoorState, pressurized, reset, clk);
  input wire commandSwitch, innerDoorState, reset, pressurized, clk;
  output reg doorState;
  always @(posedge clk) begin
    if(!reset) begin
      doorState <= 1'b0;
    end else begin
      if(commandSwitch) begin //trying to open the outer door
        if(pressurized && !innerDoorState) begin //can only do it if chamber is pressurized and inner door is closed
          doorState <= 1'b1;
        end
      end else begin
        doorState <= 1'b0; //close the door
      end
    end
  end
endmodule

module outerDoor_testbench;
  reg clk, reset, commandSwitch, innerDoorState, pressurized;
  wire doorState;
  outerDoor dut (doorState, commandSwitch, innerDoorState, pressurized, reset, clk);
  parameter ClockDelay = 2;
  initial begin //setup the clock
    clk <= 0;
    forever begin
      #(ClockDelay/2);
      clk <= ~clk;
    end
  end
  initial begin //begin testing
    $dumpfile("outerDoor.vcd");
    $dumpvars(1,dut);
    reset = 1'b0; #ClockDelay;
    reset = 1'b1; #ClockDelay;
    commandSwitch = 1'b1;
    pressurized = 1'b0;
    innerDoorState = 1'b0;
    #ClockDelay; //command is sent, but the chamber is not pressurized
    pressurized = 1'b1;
    innerDoorState = 1'b1;
    #ClockDelay; //command is sent, but inner door is open
    pressurized = 1'b0; //command is sent, but inner door is open, and the the chamber is not pressurized
    #ClockDelay;
    pressurized = 1'b1;
    innerDoorState = 1'b0;
    #ClockDelay //command is sent, and outer door is opened
    commandSwitch = 1'b0;
    #ClockDelay //close the outer door
    commandSwitch = 1'b1;
    #ClockDelay //open the outer door
    commandSwitch = 1'b0;
    #ClockDelay //close the outer door
    commandSwitch = 1'b0;
    #ClockDelay //close the outer door

    $finish;
  end
endmodule

Lab 2/EE_371_Project_2.v
// To test
`include "moveBathysphere.v"
`include "pressurizer.v"
`include "outerDoor.v"
`include "innerDoor.v"

module EE_371_Project_2(LEDR, SW, KEY, CLOCK_50);
	output reg [6:0] LEDR;
	input wire [3:0] SW;
	input wire [2:0] KEY;
	input wire CLOCK_50;
	wire [6:0] LEDRWires;


	always@(*) begin
		LEDR[0] = SW[0];
		LEDR[1] = SW[1];
		LEDR[6:2] = LEDRWires[6:2];
	end

	outerDoor outDoor(LEDRWires[2], SW[2], LEDRWires[3], LEDRWires[4], KEY[0], CLOCK_50);
	innerDoor inDoor(LEDRWires[3], SW[3], LEDRWires[2], LEDR[4], KEY[0], CLOCK_50);
	pressurizer p(LEDRWires[4], LEDRWires[2], LEDRWires[3], KEY[1], KEY[2], KEY[0], CLOCK_50);
	// Wrong order for LEDR?
	moveBathysphere sub(LEDRWires[6:5], LEDRWires[3], LEDRWires[2], SW[0], SW[1], CLOCK_50, KEY[0]);
endmodule

module EE_371_Project_2_Testbench;
	wire [6:0] LEDR;
	reg [3:0] SW;
	reg [2:0] KEY;
	reg clk;

	EE_371_Project_2 test(LEDR, SW, KEY, clk);

	parameter ClockDelay = 2;
   initial begin
		clk <= 0;
		forever begin
			#(ClockDelay/2);
			clk <= ~clk;
		end
	end

	initial begin
		$dumpfile("EE_371_Project_2.vcd");
		$dumpvars(1, test);
		// Reset
		KEY[2:0] <= 3'b110;
		SW[3:0] <= 4'b0000;
		#ClockDelay;
		#ClockDelay;
		KEY[0] = 1'b1;
		SW[0] = 1'b1; //arriving
		#ClockDelay;
		#ClockDelay;
		#ClockDelay;
		SW[2] = 1'b1;
		#ClockDelay;
		#ClockDelay;
		KEY[1] = 1'b0;
		#ClockDelay;
		#ClockDelay;
		KEY[1] = 1'b1;
		#ClockDelay;
		#ClockDelay;
		#ClockDelay;
		#ClockDelay;
		#ClockDelay;
		#ClockDelay;
		#ClockDelay;
		#ClockDelay;
		#ClockDelay;
		SW[2] = 1'b0;
		KEY[2] = 1'b0;
		#ClockDelay;
		#ClockDelay
		KEY[2] = 1'b1;
		#ClockDelay;
		#ClockDelay;
		#ClockDelay;
		#ClockDelay;
		#ClockDelay;
		#ClockDelay;
		#ClockDelay;
		#ClockDelay;
		#ClockDelay;
		#ClockDelay;
		#ClockDelay;
		#ClockDelay;
		#ClockDelay;
		#ClockDelay;
		#ClockDelay;
		#ClockDelay;
		#ClockDelay;
		#ClockDelay;
		SW[3] = 1'b1;
		#ClockDelay;
		#ClockDelay;

		$finish;
  end


endmodule

Lab 2/EE_371_Project_2.vcd
$date
	Thu Jan 25 16:24:57 2018
$end
$version
	Icarus Verilog
$end
$timescale
	1s
$end
$scope module EE_371_Project_2_Testbench $end
$scope module test $end
$var wire 1 ! CLOCK_50 $end
$var wire 3 " KEY [2:0] $end
$var wire 4 # SW [3:0] $end
$var wire 7 $ LEDRWires [6:0] $end
$var reg 7 % LEDR [6:0] $end
$upscope $end
$upscope $end
$enddefinitions $end
#0
$dumpvars
bx00 %
bxzz $
b0 #
b110 "
0!
$end
#1
b1100000 %
b11000zz $
1!
#2
0!
#3
1!
#4
0!
b1100001 %
b1 #
b111 "
#5
b1000001 %
b10000zz $
1!
#6
0!
#7
1!
#8
0!
#9
1!
#10
0!
b101 #
#11
1!
#12
0!
#13
1!
#14
0!
b101 "
#15
1!
#16
0!
#17
1!
#18
0!
b111 "
#19
1!
#20
0!
#21
1!
#22
0!
#23
1!
#24
0!
#25
1!
#26
0!
#27
1!
#28
0!
#29
1!
#30
0!
#31
b1010001 %
b10100zz $
1!
#32
0!
#33
b1010101 %
b10101zz $
1!
#34
0!
#35
b110101 %
b1101zz $
1!
#36
0!
b11 "
b1 #
#37
b110001 %
b1100zz $
1!
#38
0!
#39
1!
#40
0!
b111 "
#41
1!
#42
0!
#43
1!
#44
0!
#45
1!
#46
0!
#47
1!
#48
0!
#49
1!
#50
0!
#51
1!
#52
0!
#53
1!
#54
0!
#55
1!
#56
0!
#57
b100001 %
b1000zz $
1!
#58
0!
#59
1!
#60
0!
#61
1!
#62
0!
#63
1!
#64
0!
#65
1!
#66
0!
#67
1!
#68
0!
#69
1!
#70
0!
#71
1!
#72
0!
#73
1!
#74
0!
#75
1!
#76
0!
b1001 #
#77
b101001 %
b1010zz $
1!
#78
0!
#79
b1001 %
b10zz $
1!
