Lab 2/innerDoor.v
module innerDoor(doorState, commandSwitch, outerDoorState, pressurized, reset, clk);
  input wire commandSwitch, outerDoorState, reset, pressurized, clk;
  output reg doorState;
  always @(posedge clk) begin
    if(!reset) begin
      doorState <= 1'b0; //close the door on reset
    end else begin
      if(commandSwitch) begin //trying to open the inner door
        if(!pressurized && !outerDoorState) begin //can only do it if chamber is not pressurized and outer door is closed
          doorState <= 1'b1;
        end
      end else begin
        doorState <= 1'b0; //close the door
      end
    end
  end
endmodule

module innerDoor_testbench;
  reg clk, reset, commandSwitch, outerDoorState, pressurized;
  wire doorState;
  innerDoor dut (doorState, commandSwitch, outerDoorState, pressurized, reset, clk);
  parameter ClockDelay = 2;
  initial begin //setup the clock
    clk <= 0;
    forever begin
      #(ClockDelay/2);
      clk <= ~clk;
    end
  end
  initial begin //begin testing
    $dumpfile("innerDoor.vcd");
    $dumpvars(1,dut);
    reset = 1'b0; #ClockDelay;
    reset = 1'b1; #ClockDelay;
    commandSwitch = 1'b1;
    pressurized = 1'b1;
    outerDoorState = 1'b0;
    #ClockDelay; //command is sent, but the chamber is pressurized
    pressurized = 1'b0;
    outerDoorState = 1'b1;
    #ClockDelay //command is sent, but outer door is open
    commandSwitch = 1'b0;
    pressurized = 1'b0;
    outerDoorState = 1'b0;
    #ClockDelay //conditions are met, but the command is never sent
    commandSwitch = 1'b1;
    #ClockDelay //conditions are met, and the command is sent
    commandSwitch = 1'b0;
    #ClockDelay //command is back to off


    $finish;
  end
endmodule

Lab 2/innerDoor.vcd
$date
	Wed Jan 24 14:43:36 2018
$end
$version
	Icarus Verilog
$end
$timescale
	1s
$end
$scope module innerDoor_testbench $end
$scope module dut $end
$var wire 1 ! clk $end
$var wire 1 " commandSwitch $end
$var wire 1 # outerDoorState $end
$var wire 1 $ pressurized $end
$var wire 1 % reset $end
$var reg 1 & doorState $end
$upscope $end
$upscope $end
$enddefinitions $end
#0
$dumpvars
x&
0%
x$
x#
x"
0!
$end
#1
0&
1!
#2
0!
1%
#3
1!
#4
0!
0#
1$
1"
#5
1!
#6
0!
1#
0$
#7
1!
#8
0!
0#
0"
#9
1!
#10
0!
1"
#11
1&
1!
#12
0!
0"
#13
0&
1!
