Lab 2/keyHolder.v
module keyHolder(outputKey, inputKey, clk);
  input wire clk, inputKey;
  output reg outputKey;
  always @ (posedge clk) begin
    case(outputKey)
      1'b0: begin
        if(inputKey) begin
          outputKey = 1'b1;
        end
      end
      default: begin
        outputKey = 1'b0;
      end
    endcase
  end
endmodule

module keyHolder_testbench;
  reg clk, inputKey;
  wire outputKey;
  keyHolder dut (outputKey, inputKey, clk);
  parameter ClockDelay = 2;
  initial begin //setup the clock
    clk <= 0;
    forever begin
      #(ClockDelay/2);
      clk <= ~clk;
    end
  end
  initial begin
    $dumpfile("keyHolder.vcd");
    $dumpvars(1,dut);
    inputKey = 1'b0; #ClockDelay;
    inputKey = 1'b1; #ClockDelay;
    #ClockDelay;
    #ClockDelay;
    inputKey = 1'b0; #ClockDelay;
    #ClockDelay;
    $finish;
  end
endmodule

Lab 2/keyHolder.vcd
$date
	Tue Jan 30 12:02:54 2018
$end
$version
	Icarus Verilog
$end
$timescale
	1s
$end
$scope module keyHolder_testbench $end
$scope module dut $end
$var wire 1 ! clk $end
$var wire 1 " inputKey $end
$var reg 1 # outputKey $end
$upscope $end
$upscope $end
$enddefinitions $end
#0
$dumpvars
x#
0"
0!
$end
#1
0#
1!
#2
0!
1"
#3
1#
1!
#4
0!
#5
0#
1!
#6
0!
#7
1#
1!
#8
0!
0"
#9
0#
1!
