Lab 2/moveBathysphere.v
//11 is off, 10, is outside, 01 is chamber, 00 is inside
module moveBathysphere (bathysphereState, innerDoorState, outerDoorState, arriving, departing, clk, reset);
  input wire innerDoorState, outerDoorState, arriving, departing, clk, reset;
  output reg [1:0] bathysphereState;
  always @ (posedge clk) begin
    if(arriving ^ departing) begin
        case(bathysphereState)
          2'b11: begin
            if(arriving) begin
              bathysphereState = 2'b10;
            end else begin
              bathysphereState = 2'b00;
            end
          end
          2'b10: begin
            if(arriving && !outerDoorState) begin
              bathysphereState = 2'b01;
            end
            if(departing) begin
              bathysphereState = 2'b11;
            end
          end
          2'b01: begin
            if(arriving && !innerDoorState) begin
              bathysphereState = 2'b00;
            end
            if(departing && !outerDoorState) begin
              bathysphereState = 2'b10;
            end
          end
          2'b00: begin
            if(departing && !innerDoorState) begin
              bathysphereState = 2'b01;
            end
            if(arriving) begin
              bathysphereState = 2'b11;
            end
          end
          default: begin
            bathysphereState = 2'b11;
          end
        endcase
      end else begin
        bathysphereState = 2'b11;
      end
  end
endmodule

module moveBathysphere_testbench;
  reg innerDoorState, outerDoorState, arriving, departing, clk, reset;
  wire [1:0] bathysphereState;
  moveBathysphere dut (bathysphereState, innerDoorState, outerDoorState, arriving, departing, clk, reset);
  parameter ClockDelay = 2;
  initial begin //setup the clock
    clk <= 0;
    forever begin
      #(ClockDelay/2);
      clk <= ~clk;
    end
  end
  initial begin //begin testing
    $dumpfile("moveBathysphere.vcd");
    $dumpvars(1,dut);
    innerDoorState = 1'b0;
    outerDoorState = 1'b0;
    arriving = 1'b0;
    departing = 1'b0;
    reset = 1'b0; #ClockDelay;
    reset = 1'b1; #ClockDelay;
    #ClockDelay;
    arriving = 1'b1;
    #ClockDelay;
    departing = 1'b1;
    #ClockDelay;
    arriving = 1'b0;
    #ClockDelay;
    #ClockDelay;
    #ClockDelay;
    innerDoorState = 1'b1;
    #ClockDelay;
    #ClockDelay;
    #ClockDelay;
    innerDoorState = 1'b0;
    outerDoorState = 1'b1;
    #ClockDelay;
    #ClockDelay;
    arriving = 1'b1;
    #ClockDelay;
    outerDoorState = 1'b0;
    departing = 1'b0;
    innerDoorState = 1'b1;
    #ClockDelay;
    #ClockDelay;
    #ClockDelay;
    innerDoorState = 1'b0;
    outerDoorState = 1'b1;
    #ClockDelay;
    #ClockDelay;
    #ClockDelay;
    $finish;
  end
endmodule

Lab 2/moveBathysphere.vcd
$date
	Thu Jan 25 14:28:32 2018
$end
$version
	Icarus Verilog
$end
$timescale
	1s
$end
$scope module moveBathysphere_testbench $end
$scope module dut $end
$var wire 1 ! arriving $end
$var wire 1 " clk $end
$var wire 1 # departing $end
$var wire 1 $ innerDoorState $end
$var wire 1 % outerDoorState $end
$var wire 1 & reset $end
$var reg 2 ' bathysphereState [1:0] $end
$upscope $end
$upscope $end
$enddefinitions $end
#0
$dumpvars
bx '
0&
0%
0$
0#
0"
0!
$end
#1
b11 '
1"
#2
0"
1&
#3
1"
#4
0"
#5
1"
#6
0"
1!
#7
b10 '
1"
#8
0"
1#
#9
b11 '
1"
#10
0"
0!
#11
b0 '
1"
#12
0"
#13
b1 '
1"
#14
0"
#15
b10 '
1"
#16
0"
1$
#17
b11 '
1"
#18
0"
#19
b0 '
1"
#20
0"
#21
1"
#22
0"
1%
0$
#23
b1 '
1"
#24
0"
#25
1"
#26
0"
1!
#27
b11 '
1"
#28
0"
1$
0#
0%
#29
b10 '
1"
#30
0"
#31
b1 '
1"
#32
0"
#33
1"
#34
0"
1%
0$
#35
b0 '
1"
#36
0"
#37
b11 '
1"
#38
0"
#39
b10 '
1"
