Lab 2/outerDoor.v
//1 means open, 0 means closed
module outerDoor(doorState, commandSwitch, innerDoorState, pressurized, reset, clk);
  input wire commandSwitch, innerDoorState, reset, pressurized, clk;
  output reg doorState;
  always @(posedge clk) begin
    if(!reset) begin
      doorState <= 1'b0;
    end else begin
      if(commandSwitch) begin //trying to open the outer door
        if(pressurized && !innerDoorState) begin //can only do it if chamber is pressurized and inner door is closed
          doorState <= 1'b1;
        end
      end else begin
        doorState <= 1'b0; //close the door
      end
    end
  end
endmodule

module outerDoor_testbench;
  reg clk, reset, commandSwitch, innerDoorState, pressurized;
  wire doorState;
  outerDoor dut (doorState, commandSwitch, innerDoorState, pressurized, reset, clk);
  parameter ClockDelay = 2;
  initial begin //setup the clock
    clk <= 0;
    forever begin
      #(ClockDelay/2);
      clk <= ~clk;
    end
  end
  initial begin //begin testing
    $dumpfile("outerDoor.vcd");
    $dumpvars(1,dut);
    reset = 1'b0; #ClockDelay;
    reset = 1'b1; #ClockDelay;
    commandSwitch = 1'b1;
    pressurized = 1'b0;
    innerDoorState = 1'b0;
    #ClockDelay; //command is sent, but the chamber is not pressurized
    pressurized = 1'b1;
    innerDoorState = 1'b1;
    #ClockDelay; //command is sent, but inner door is open
    pressurized = 1'b0; //command is sent, but inner door is open, and the the chamber is not pressurized
    #ClockDelay;
    pressurized = 1'b1;
    innerDoorState = 1'b0;
    #ClockDelay //command is sent, and outer door is opened
    commandSwitch = 1'b0;
    #ClockDelay //close the outer door
    commandSwitch = 1'b1;
    #ClockDelay //open the outer door
    commandSwitch = 1'b0;
    #ClockDelay //close the outer door
    commandSwitch = 1'b0;
    #ClockDelay //close the outer door

    $finish;
  end
endmodule

Lab 2/outerDoor.vcd
$date
	Tue Jan 23 14:10:54 2018
$end
$version
	Icarus Verilog
$end
$timescale
	1s
$end
$scope module outerDoor_testbench $end
$scope module dut $end
$var wire 1 ! clk $end
$var wire 1 " commandSwitch $end
$var wire 1 # innerDoorState $end
$var wire 1 $ pressurized $end
$var wire 1 % reset $end
$var reg 1 & doorState $end
$upscope $end
$upscope $end
$enddefinitions $end
#0
$dumpvars
x&
0%
x$
x#
x"
0!
$end
#1
0&
1!
#2
0!
1%
#3
1!
#4
0!
0#
0$
1"
#5
1!
#6
0!
1#
1$
#7
1!
#8
0!
0$
#9
1!
#10
0!
0#
1$
#11
1&
1!
#12
0!
0"
#13
0&
1!
#14
0!
1"
#15
1&
1!
#16
0!
0"
#17
0&
1!
