Lab 2/pressurizer.v
module pressurizer (pressurized, innerDoorState, outerDoorState, pressurizeSignal, depressurizeSignal, reset, clk);
  input wire innerDoorState, outerDoorState, pressurizeSignal, depressurizeSignal, reset, clk;
  output reg pressurized;
  reg[1:0] pressurizeState; //00 means depressurize, 01 means pressurize, 10 means wait
  reg[3:0] count;
  always @ (*) begin
    case(pressurizeState)
        2'b00: begin
          if(!pressurized) begin
            pressurizeState <= 2'b10;
          end
        end
        2'b01: begin
          if(pressurized) begin
            pressurizeState <= 2'b10;
          end
        end
        2'b10: begin
          if(!pressurizeSignal && !innerDoorState && !outerDoorState && !pressurized) begin
            pressurizeState <= 2'b01;
          end else if(!depressurizeSignal && !innerDoorState && !outerDoorState && pressurized) begin
            pressurizeState <= 2'b00;
          end
        end
        default: begin
          pressurizeState <= 2'b10;
        end
    endcase
  end
  always @ (posedge clk) begin
    if(!reset) begin
      count <= 4'd0;
      pressurized <= 1'b0;
    end else begin
      if(pressurizeState == 2'b01) begin
        if(!outerDoorState && !innerDoorState) begin //can only pressurize if the doors are closed
          if(count == 4'd7) begin //pressurize the chamber after 7 ticks of the clock
            pressurized <= 1'b1;
            count <= 4'd0;
          end else begin
            count <= count + 1'b1;
          end
        end
      end else if(pressurizeState == 2'b00) begin
        if(!outerDoorState && !innerDoorState) begin //can only depressurize if doors are closed
          if(count == 4'd8) begin
            pressurized <= 1'b0;
            count <= 4'd0;
          end else begin
            count <= count + 1'b1;
          end
        end
      end
    end
  end
endmodule

module pressurizer_testbench;
  wire pressurized;
  reg clk, reset, pressurizeSignal, depressurizeSignal, innerDoorState, outerDoorState;
  pressurizer dut (pressurized, innerDoorState, outerDoorState, pressurizeSignal, depressurizeSignal, reset, clk);
  parameter ClockDelay = 2;
  initial begin //setup the clock
    clk <= 0;
    forever begin
      #(ClockDelay/2);
      clk <= ~clk;
    end
  end
  integer i;
  initial begin
    $dumpfile("pressurizer.vcd");
    $dumpvars(1,dut);
    reset <= 1'b0; #(2*ClockDelay);
    reset <= 1'b1; #ClockDelay;
    innerDoorState <= 1'b0;
    outerDoorState <= 1'b0;
    depressurizeSignal <= 1'b1;
    pressurizeSignal <= 1'b1;
    #ClockDelay;
    pressurizeSignal <= 1'b0; //begin pressurization
    #ClockDelay;
    pressurizeSignal <= 1'b1;
    for(i = 0; i < 10; i = i + 1)begin
        #ClockDelay;
    end
    #ClockDelay;
    depressurizeSignal <= 1'b0;
    #ClockDelay;
    depressurizeSignal <= 1'b1;
    for(i = 0; i < 8; i = i + 1)begin
      #ClockDelay;
    end
    #ClockDelay;
    pressurizeSignal <= 1'b0; //begin pressurization but inner door is open
    innerDoorState <= 1'b1;
    #ClockDelay;
    pressurizeSignal <= 1'b1;
    #ClockDelay;
    #ClockDelay;
    #ClockDelay;
    depressurizeSignal <= 1'b0; //begin depressurization but inner door is open
    #ClockDelay;
    #ClockDelay;
    depressurizeSignal <= 1'b1;
    #ClockDelay;
    #ClockDelay;
    innerDoorState <= 1'b0;
    depressurizeSignal <= 1'b0;
    #ClockDelay;
    #ClockDelay;
    #ClockDelay;
    depressurizeSignal <= 1'b1;
    #ClockDelay;
    #ClockDelay;
    $finish;
  end
endmodule

Lab 2/pressurizer.vcd
$date
	Thu Jan 25 13:28:12 2018
$end
$version
	Icarus Verilog
$end
$timescale
	1s
$end
$scope module pressurizer_testbench $end
$scope module dut $end
$var wire 1 ! clk $end
$var wire 1 " depressurizeSignal $end
$var wire 1 # innerDoorState $end
$var wire 1 $ outerDoorState $end
$var wire 1 % pressurizeSignal $end
$var wire 1 & reset $end
$var reg 4 ' count [3:0] $end
$var reg 2 ( pressurizeState [1:0] $end
$var reg 1 ) pressurized $end
$upscope $end
$upscope $end
$enddefinitions $end
#0
$dumpvars
x)
bx (
bx '
0&
x%
x$
x#
x"
0!
$end
#1
b10 (
0)
b0 '
1!
#2
0!
#3
1!
#4
0!
1&
#5
1!
#6
0!
1%
1"
0$
0#
#7
1!
#8
b1 (
0!
0%
#9
b1 '
1!
#10
0!
1%
#11
b10 '
1!
#12
0!
#13
b11 '
1!
#14
0!
#15
b100 '
1!
#16
0!
#17
b101 '
1!
#18
0!
#19
b110 '
1!
#20
0!
#21
b111 '
1!
#22
0!
#23
b10 (
b0 '
1)
1!
#24
0!
#25
1!
#26
0!
#27
1!
#28
0!
#29
1!
#30
0!
#31
1!
#32
b0 (
0!
0"
#33
b1 '
1!
#34
0!
1"
#35
b10 '
1!
#36
0!
#37
b11 '
1!
#38
0!
#39
b100 '
1!
#40
0!
#41
b101 '
1!
#42
0!
#43
b110 '
1!
#44
0!
#45
b111 '
1!
#46
0!
#47
b1000 '
1!
#48
0!
#49
b10 (
b0 '
0)
1!
#50
0!
#51
1!
#52
0!
1#
0%
#53
1!
#54
0!
1%
#55
1!
#56
0!
#57
1!
#58
0!
#59
1!
#60
0!
0"
#61
1!
#62
0!
#63
1!
#64
0!
1"
#65
1!
#66
0!
#67
1!
#68
0!
0"
0#
#69
1!
#70
0!
#71
1!
#72
0!
#73
1!
#74
0!
1"
