Lab 2/pressurizer.v
module pressurizer (pressurized, innerDoorState, outerDoorState, pressurizeSignal, depressurizeSignal, reset, clk);
  input wire innerDoorState, outerDoorState, pressurizeSignal, depressurizeSignal, reset, clk;
  output reg pressurized;
  reg[1:0] pressurizeState; //00 means depressurize, 01 means pressurize, 10 means wait
  reg[3:0] count;
  always @ (*) begin
    case(pressurizeState)
        2'b00: begin
          if(!pressurized) begin
            pressurizeState <= 2'b10;
          end
        end
        2'b01: begin
          if(pressurized) begin
            pressurizeState <= 2'b10;
          end
        end
        2'b10: begin
          if(!pressurizeSignal) begin
            pressurizeState <= 2'b01;
          end else if(!depressurizeSignal) begin
            pressurizeState <= 2'b00;
          end
        end
        default: begin
          pressurizeState <= 2'b10;
        end
    endcase
  end
  always @ (posedge clk) begin
    if(!reset) begin
      count <= 4'd0;
      pressurized <= 1'b0;
    end else begin
      if(pressurizeState == 2'b01) begin
        if(!outerDoorState && !innerDoorState) begin //can only pressurize if the doors are closed
          if(count == 4'd7) begin //pressurize the chamber after 7 ticks of the clock
            pressurized <= 1'b1;
            count <= 4'd0;
          end else begin
            count <= count + 1'b1;
          end
        end
      end else if(pressurizeState == 2'b00) begin
        if(!outerDoorState && !innerDoorState) begin //can only depressurize if doors are closed
          if(count == 4'd8) begin
            pressurized <= 1'b0;
            count <= 4'd0;
          end else begin
            count <= count + 1'b1;
          end
        end
      end
    end
  end
endmodule

module pressurizer_testbench;
  wire pressurized;
  reg clk, reset, pressurizeSignal, depressurizeSignal, innerDoorState, outerDoorState;
  pressurizer dut (pressurized, innerDoorState, outerDoorState, pressurizeSignal, depressurizeSignal, reset, clk);
  parameter ClockDelay = 2;
  initial begin //setup the clock
    clk <= 0;
    forever begin
      #(ClockDelay/2);
      clk <= ~clk;
    end
  end
  integer i;
  initial begin
    $dumpfile("pressurizer.vcd");
    $dumpvars(1,dut);
    reset = 1'b0; #(2*ClockDelay);
    reset = 1'b1; #ClockDelay;
    innerDoorState = 1'b0;
    outerDoorState = 1'b0;
    depressurizeSignal = 1'b1;
    pressurizeSignal = 1'b1;
    #ClockDelay;
    pressurizeSignal = 1'b0; //begin pressurization
    for(i = 0; i < 10; i = i + 1)begin
        #ClockDelay;
    end
    $finish;
  end
endmodule

Lab 2/pressurizer.vcd
$date
	Wed Jan 24 16:52:31 2018
$end
$version
	Icarus Verilog
$end
$timescale
	1s
$end
$scope module pressurizer_testbench $end
$scope module dut $end
$var wire 1 ! clk $end
$var wire 1 " depressurizeSignal $end
$var wire 1 # innerDoorState $end
$var wire 1 $ outerDoorState $end
$var wire 1 % pressurizeSignal $end
$var wire 1 & reset $end
$var reg 4 ' count [3:0] $end
$var reg 2 ( pressurizeState [1:0] $end
$var reg 1 ) pressurized $end
$upscope $end
$upscope $end
$enddefinitions $end
#0
$dumpvars
x)
bx (
bx '
0&
x%
x$
x#
x"
0!
$end
#1
b10 (
0)
b0 '
1!
#2
0!
#3
1!
#4
0!
1&
#5
1!
#6
0!
1%
1"
0$
0#
#7
1!
#8
b1 (
0!
0%
#9
b1 '
1!
#10
0!
#11
b10 '
1!
#12
0!
#13
b11 '
1!
#14
0!
#15
b100 '
1!
#16
0!
#17
b101 '
1!
#18
0!
#19
b110 '
1!
#20
0!
#21
b111 '
1!
