Lab4/bitIdentifierCount.v
module bitIdentifierCount(characterReceived, enable, bitReceived, clk, reset);
  output reg characterReceived;
  input wire enable, bitReceived, clk, reset;
  reg [3:0] bitCount;
  reg characterReceivedState;
  always@(posedge clk) begin
    if(reset || !enable) begin
      characterReceived <= 1'b0;
      bitCount <= 4'b0000;
    end else begin
      characterReceived <= characterReceivedState;
      if(enable && bitReceived) begin
        bitCount <= bitCount + 1'b1;
      end
    end
  end
  always@(*) begin
    case(characterReceivedState)
      1'b1: begin
        characterReceivedState = 1'b0;
      end
      1'b0: begin
        if(bitCount == 4'b0111 && enable) begin
          characterReceivedState = 1'b1;
        end
      end
      default: begin
        characterReceivedState = 1'b0;
      end
    endcase
  end
endmodule

module bitIdentifierCount_testbench;
  wire characterReceived;
  reg enable, bitReceived, clk, reset;

  bitIdentifierCount dut (characterReceived, enable, bitReceived, clk, reset);

  parameter ClockDelay = 2;
  initial begin //setup the clock
    clk <= 0;
    forever begin
      #(ClockDelay/2);
      clk <= ~clk;
    end
  end
  integer i;

  initial begin
    $dumpfile("bitIdentifierCount.vcd");
    $dumpvars(1,dut);
    reset <= 1'b1;
    bitReceived <= 1'b0;
    enable <= 1'b0;
    #ClockDelay;
    reset <= 1'b0;
    #ClockDelay;
    enable <= 1'b1;
    #ClockDelay;
    bitReceived = 1'b1;
    for(i = 0; i < 9; i++) begin
      #ClockDelay;
    end
    $finish;
  end
endmodule

Lab4/bitIdentifierCount.vcd
$date
	Wed Feb 21 15:28:24 2018
$end
$version
	Icarus Verilog
$end
$timescale
	1s
$end
$scope module bitIdentifierCount_testbench $end
$scope module dut $end
$var wire 1 ! bitReceived $end
$var wire 1 " clk $end
$var wire 1 # enable $end
$var wire 1 $ reset $end
$var reg 4 % bitCount [3:0] $end
$var reg 1 & characterReceived $end
$var reg 1 ' characterReceivedState $end
$upscope $end
$upscope $end
$enddefinitions $end
#0
$dumpvars
0'
x&
bx %
1$
0#
0"
0!
$end
#1
b0 %
0&
1"
#2
0"
0$
#3
1"
#4
0"
1#
#5
1"
#6
0"
1!
#7
b1 %
1"
#8
0"
#9
b10 %
1"
#10
0"
#11
b11 %
1"
#12
0"
#13
b100 %
1"
#14
0"
#15
b101 %
1"
#16
0"
#17
b110 %
1"
#18
0"
#19
1'
b111 %
1"
#20
0"
#21
0'
b1000 %
1&
1"
#22
0"
#23
b1001 %
0&
1"
