Lab4/bitIdentifierCountReceive.v
module bitIdentifierCountReceive(characterReceived, enable, bitReceived, bitCount, clk, reset);
  output reg characterReceived;
  input wire enable, bitReceived, clk, reset;
  output reg [3:0] bitCount;
  reg characterReceivedState;
  always@(posedge clk) begin
    if(reset) begin
      characterReceived <= 1'b0;
      bitCount <= 4'b000;
    end else begin
      characterReceived <= characterReceivedState;
      if(enable && bitReceived) begin
        bitCount <= bitCount + 1'b1;
      end
    end
  end
  always@(*) begin
    case(characterReceivedState)
      1'b1: begin
        characterReceivedState = 1'b0;
      end
      1'b0: begin
        if(bitCount == 4'b1010 && enable) begin
          characterReceivedState = 1'b1;
        end
      end
      default: begin
        characterReceivedState = 1'b0;
      end
    endcase
  end
endmodule

Lab4/startBitDetect.v
//module that identifies the start bit of a sent character. allows the counting
//circuits to begin running.
module startBitDetect(startBitDetected, characterReceived, data, bitCount, clk, reset);
  output reg startBitDetected;
  input wire characterReceived, data, clk, reset;
  input wire [3:0] bitCount;

  reg readingData;

  always@(posedge clk) begin
    if(reset) begin
      startBitDetected = 1'b0;
      readingData = 1'b0;
    end else begin
      startBitDetected <= readingData;
    end
  end

  always@(*) begin //readingData is a state machine that keeps track of whether the start bit has been detected
    case(readingData)
      1'b1: begin
        if(bitCount == 11) begin //only stop reading when the entirety of the character has been received
          readingData = 1'b0;
        end
      end
      1'b0: begin
        if(!data) begin //begin reading when receiving the start bit
          readingData = 1'b1;
        end
      end
      default: begin
        readingData = 1'b0;
      end
    endcase
  end
endmodule

// module startBitDetect_testbench;
//   wire startBitDetected;
//   reg characterReceived, data, clk, reset;

//   startBitDetect dut(startBitDetected, characterReceived, data, clk, reset);

//   parameter ClockDelay = 2;
//   initial begin //setup the clock
//     clk <= 0;
//     forever begin
//       #(ClockDelay/2);
//       clk <= ~clk;
//     end
//   end

//   initial begin
//     $dumpfile("startBitDetect.vcd");
//     $dumpvars(1,dut);
//     reset <= 1'b1;
//     #ClockDelay;
//     reset <= 1'b0;
//     #ClockDelay;
//     data = 1'b1;
//     characterReceived = 1'b0;
//     #ClockDelay;
//     characterReceived = 1'b1;
//     #ClockDelay;
//     characterReceived = 1'b0;
//     data = 1'b0;
//     #ClockDelay;
//     #ClockDelay;
//     #ClockDelay;
//     characterReceived = 1'b1;
//     #ClockDelay;
//     $finish;
//   end
// endmodule

Lab4/bitSampleCount.v
module bitSampleCount(clockControl, bitIncrementControl, enable, clk, reset);
  output reg clockControl, bitIncrementControl;
  input wire enable, clk, reset;
  reg [3:0] count;
  always@(posedge clk) begin
    if(reset) begin
      clockControl <= 1'b0;
      count <= 4'b0000;
      bitIncrementControl <= 1'b0;
    end else begin
      if(enable) begin
        clockControl <= count[3];
        if(count == 4'b1111)begin
          count <= 4'b0000;
          bitIncrementControl = 1'b1;
        end else begin
          count <= count + 1'b1;
          bitIncrementControl <= 4'b0000;
        end
      end else begin
        clockControl <= 1'b0;
        count <= 4'b0000;
        bitIncrementControl = 1'b0;
      end
    end
  end
endmodule

Lab4/bitIdentifierCount.v
module bitIdentifierCount(characterReceived, enable, bitReceived, clk, reset);
  output reg characterReceived;
  input wire enable, bitReceived, clk, reset;
  reg [3:0] bitCount;
  reg characterReceivedState;
  always@(posedge clk) begin
    if(reset || !enable) begin
      characterReceived <= 1'b0;
      bitCount <= 4'b0000;
    end else begin
      characterReceived <= characterReceivedState;
      if(enable && bitReceived) begin
        bitCount <= bitCount + 1'b1;
      end
    end
  end
  always@(*) begin
    case(characterReceivedState)
      1'b1: begin
        characterReceivedState = 1'b0;
      end
      1'b0: begin
        if(bitCount == 4'b0111 && enable) begin
          characterReceivedState = 1'b1;
        end
      end
      default: begin
        characterReceivedState = 1'b0;
      end
    endcase
  end
endmodule

module bitIdentifierCount_testbench;
  wire characterReceived;
  reg enable, bitReceived, clk, reset;

  bitIdentifierCount dut (characterReceived, enable, bitReceived, clk, reset);

  parameter ClockDelay = 2;
  initial begin //setup the clock
    clk <= 0;
    forever begin
      #(ClockDelay/2);
      clk <= ~clk;
    end
  end
  integer i;

  initial begin
    $dumpfile("bitIdentifierCount.vcd");
    $dumpvars(1,dut);
    reset <= 1'b1;
    bitReceived <= 1'b0;
    enable <= 1'b0;
    #ClockDelay;
    reset <= 1'b0;
    #ClockDelay;
    enable <= 1'b1;
    #ClockDelay;
    bitReceived = 1'b1;
    for(i = 0; i < 9; i++) begin
      #ClockDelay;
    end
    $finish;
  end
endmodule

Lab4/s2p.v
module s2p(parallelOut, serialIn, charReceived, reset, clk);
  output reg [7:0] parallelOut;
  input wire serialIn, charReceived, reset, clk;

  reg [9:0] allData;
  reg [3:0] count;

  always@(posedge clk) begin
    if(reset) begin
      parallelOut <= 8'd0;
    end else begin
      allData[0] <= serialIn;
      allData[1] <= allData[0];
      allData[2] <= allData[1];
      allData[3] <= allData[2];
      allData[4] <= allData[3];
      allData[5] <= allData[4];
      allData[6] <= allData[5];
      allData[7] <= allData[6];
      allData[8] <= allData[7];
      allData[9] <= allData[8];
    end
  end

  always@(posedge charReceived)begin
    parallelOut[0] <= allData[1];
    parallelOut[1] <= allData[2];
    parallelOut[2] <= allData[3];
    parallelOut[3] <= allData[4];
    parallelOut[4] <= allData[5];
    parallelOut[5] <= allData[6];
    parallelOut[6] <= allData[7];
    parallelOut[7] <= allData[8];
  end
endmodule

// module s2p_testbench;
//   wire [7:0] parallelOut;
//   reg serialIn, charReceived, reset, clk;

//   s2p dut(parallelOut, serialIn, charReceived, reset, clk);

//   parameter ClockDelay = 2;
//   initial begin //setup the clock
//     clk <= 0;
//     forever begin
//       #(ClockDelay/2);
//       clk <= ~clk;
//     end
//   end
//   integer i;
//   initial begin
//     $dumpfile("s2p.vcd");
//     $dumpvars(1,dut);
//     reset <= 1'b1;
//     charReceived <= 1'b0;
//     serialIn <= 1'b1;
//     #ClockDelay;
//     reset <= 1'b0;
//     #ClockDelay;
//     for(i = 0; i < 11; i++) begin
//       serialIn <= i % 2;
//       charReceived <= i == 10;
//       #ClockDelay;
//     end
//     $finish;
//   end
// endmodule

Lab4/p2s.v
module p2s(serialOut, parallelIn, load, clk, reset);
  output reg serialOut;
  input wire [7:0] parallelIn;
  input load, clk, reset;

  reg [9:0] loadBuffer;
  initial serialOut <= 1'b1;

  always@(posedge clk) begin
    if(reset) begin
      serialOut <= 1'b1;
      loadBuffer <= 10'b1111111111;
    end else begin
      serialOut <= loadBuffer[9];
      loadBuffer[9] <= loadBuffer[8];
      loadBuffer[8] <= loadBuffer[7];
      loadBuffer[7] <= loadBuffer[6];
      loadBuffer[6] <= loadBuffer[5];
      loadBuffer[5] <= loadBuffer[4];
      loadBuffer[4] <= loadBuffer[3];
      loadBuffer[3] <= loadBuffer[2];
      loadBuffer[2] <= loadBuffer[1];
      loadBuffer[1] <= loadBuffer[0];
      loadBuffer[0] <= 1'b1;
    end
  end
  always@(posedge load) begin
     loadBuffer[0] <= 1'b1;
     loadBuffer[1] <= parallelIn[0];
     loadBuffer[2] <= parallelIn[1];
     loadBuffer[3] <= parallelIn[2];
     loadBuffer[4] <= parallelIn[3];
     loadBuffer[5] <= parallelIn[4];
     loadBuffer[6] <= parallelIn[5];
     loadBuffer[7] <= parallelIn[6];
     loadBuffer[8] <= parallelIn[7];
     loadBuffer[9] <= 1'b0;
  end
endmodule

// module p2s_testbench;
//   wire serialOut;
//   reg [7:0] parallelIn;
//   reg load, clk, reset;

//   p2s dut(serialOut, parallelIn, load, clk, reset);

//   parameter ClockDelay = 2;
//   initial begin //setup the clock
//     clk <= 0;
//     forever begin
//       #(ClockDelay/2);
//       clk <= ~clk;
//     end
//   end
//   integer i;
//   initial begin
//     $dumpfile("p2s.vcd");
//     $dumpvars(1,dut);
//     reset <= 1'b1;
//     load <= 1'b0;
//     #ClockDelay;
//     reset <= 1'b0;
//     #ClockDelay;
//     parallelIn <= 8'b10110101;
//     load <= 1'b1;
//     #ClockDelay;
//     parallelIn <= 8'b10001101;
//     load <= 1'b0;
//     for(i = 0; i < 10; i++) begin
//       #ClockDelay;
//     end
//     $finish;
//   end
// endmodule

Lab4/networkHardware.v
`include "p2s.v"
`include "s2p.v"
`include "startBitDetect.v"
`include "bitSampleCount.v"
`include "bitIdentifierCount.v"
`include "bitIdentifierCountReceive.v"
module networkHardware(reset, clk, transmitEnable, parallelDataOut, load, parallelDataIn, characterReceived, characterSent, serialDataIn, serialDataOut);
	input wire reset, clk;
	input wire serialDataIn;
	output wire serialDataOut;
	input wire [7:0] parallelDataOut;
	input wire transmitEnable;
	input wire load;
	output wire characterReceived, characterSent;
	output wire [7:0] parallelDataIn;
	wire BSCClockOut, BSCClockIn;
	wire startBitDetected;
	wire [3:0] bitCountIn, bitCountOut;

	bitIdentifierCount outDataBIC(characterSent, transmitEnable, BSCClockOut, bitCountOut, clk, reset);
	bitSampleCount outDataBSC(BSCClockOut, transmitEnable, clk, reset);
	p2s dataOut(serialDataOut, parallelDataOut, load, BSCClockOut, reset);
	
	s2p dataIn(parallelDataIn, serialDataIn, characterReceived, reset, BSCClockIn);
	bitIdentifierCount inDataBIC(characterReceived, startBitDetected, BSCClockIn, bitCountIn, clk, reset);
	bitSampleCount inDataBSC(BSCClockIn, startBitDetected, clk, reset);
	startBitDetect detector(startBitDetected, characterReceived, serialDataIn, bitCountIn, clk, reset);
endmodule

module networkHardware_testbench;
	reg reset;	
	reg clk;
	reg serialDataIn;
	wire serialDataOut;
	reg [7:0] parallelDataOut;
	reg transmitEnable;
	reg load;
	wire characterReceived, characterSent;
 	wire [7:0] parallelDataIn;
 	reg nClk;

 	networkHardware dut(reset, clk, transmitEnable, parallelDataOut, load, parallelDataIn, characterReceived, characterSent, serialDataIn, serialDataOut); 
 	always@(posedge clk) begin
 		serialDataIn <= serialDataOut;
 	end
 	parameter ClockDelay = 2;
  	initial begin //setup the clock
    	clk <= 0;
    	forever begin
      		#(ClockDelay/2);
      		clk <= ~clk;
      	end
  	end
  	integer i;
  	initial begin
	   $dumpfile("networkHardware.vcd");
	   $dumpvars(1,dut);
	   reset <= 1'b1;
	   serialDataIn <= 1'b1;
	   transmitEnable <= 1'b0;
	   load <= 1'b0;
	   parallelDataOut <= 8'd0;
	   #ClockDelay;
	   reset <= 1'b0;
	   #ClockDelay;
	   $display("beginning transmission at: %d", $time);
	   transmitEnable <= 1'b1;
	   parallelDataOut <= 8'b01010101;
	   load <= 1'b1;
	   #ClockDelay;
	   for(i = 0; i < 176; i++) begin
	   	#ClockDelay;
	   end
	   transmitEnable <= 1'b0;
	   load <= 1'b0;
	   #ClockDelay;
	   transmitEnable <= 1'b1;
	   parallelDataOut <= 8'b10101010;
	   load <= 1'b1;
	   #ClockDelay;
	   for(i = 0; i < 176; i++) begin
	   	#ClockDelay;
	   end
	   transmitEnable <= 1'b0;
	   #ClockDelay;
	   $finish;
	end
endmodule

Lab4/networkHardware.vcd
$date
	Sat Mar  3 11:24:01 2018
$end
$version
	Icarus Verilog
$end
$timescale
	1s
$end
$scope module networkHardware_testbench $end
$scope module dut $end
$var wire 1 ! clk $end
$var wire 1 " load $end
$var wire 8 # parallelDataOut [7:0] $end
$var wire 1 $ reset $end
$var wire 1 % serialDataIn $end
$var wire 1 & transmitEnable $end
$var wire 1 ' startBitDetected $end
$var wire 1 ( serialDataOut $end
$var wire 8 ) parallelDataIn [7:0] $end
$var wire 1 * characterSent $end
$var wire 1 + characterReceived $end
$var wire 4 , bitCountOut [3:0] $end
$var wire 4 - bitCountIn [3:0] $end
$var wire 1 . BSCClockOut $end
$var wire 1 / BSCClockIn $end
$upscope $end
$upscope $end
$enddefinitions $end
#0
$dumpvars
x/
x.
bx -
bx ,
x+
x*
bx )
1(
x'
0&
1%
1$
b0 #
0"
0!
$end
#1
0*
b0 ,
0.
0+
b0 -
0/
0'
1!
#2
0!
0$
#3
1!
#4
0!
1"
b1010101 #
1&
#5
1!
#6
0!
#7
1!
#8
0!
#9
1!
#10
0!
#11
1!
#12
0!
#13
1!
#14
0!
#15
1!
#16
0!
#17
1!
#18
0!
#19
b1 ,
0(
1.
1!
#20
0!
#21
0%
1!
#22
0!
#23
1'
1!
#24
0!
#25
1!
#26
0!
#27
1!
#28
0!
#29
1!
#30
0!
#31
1!
#32
0!
#33
1!
#34
0!
#35
0.
1!
#36
0!
#37
1!
#38
0!
#39
b1 -
1/
1!
#40
0!
#41
1!
#42
0!
#43
1!
#44
0!
#45
1!
#46
0!
#47
1!
#48
0!
#49
1!
#50
0!
#51
b10 ,
1.
1!
#52
0!
#53
1!
#54
0!
#55
0/
1!
#56
0!
#57
1!
#58
0!
#59
1!
#60
0!
#61
1!
#62
0!
#63
1!
#64
0!
#65
1!
#66
0!
#67
0.
1!
#68
0!
#69
1!
#70
0!
#71
b10 -
1/
1!
#72
0!
#73
1!
#74
0!
#75
1!
#76
0!
#77
1!
#78
0!
#79
1!
#80
0!
#81
1!
#82
0!
#83
b11 ,
1(
1.
1!
#84
0!
#85
1%
1!
#86
0!
#87
0/
1!
#88
0!
#89
1!
#90
0!
#91
1!
#92
0!
#93
1!
#94
0!
#95
1!
#96
0!
#97
1!
#98
0!
#99
0.
1!
#100
0!
#101
1!
#102
0!
#103
b11 -
1/
1!
#104
0!
#105
1!
#106
0!
#107
1!
#108
0!
#109
1!
#110
0!
#111
1!
#112
0!
#113
1!
#114
0!
#115
0(
b100 ,
1.
1!
#116
0!
#117
0%
1!
#118
0!
#119
0/
1!
#120
0!
#121
1!
#122
0!
#123
1!
#124
0!
#125
1!
#126
0!
#127
1!
#128
0!
#129
1!
#130
0!
#131
0.
1!
#132
0!
#133
1!
#134
0!
#135
b100 -
1/
1!
#136
0!
#137
1!
#138
0!
#139
1!
#140
0!
#141
1!
#142
0!
#143
1!
#144
0!
#145
1!
#146
0!
#147
b101 ,
1(
1.
1!
#148
0!
#149
1%
1!
#150
0!
#151
0/
1!
#152
0!
#153
1!
#154
0!
#155
1!
#156
0!
#157
1!
#158
0!
#159
1!
#160
0!
#161
1!
#162
0!
#163
0.
1!
#164
0!
#165
1!
#166
0!
#167
b101 -
1/
1!
#168
0!
#169
1!
#170
0!
#171
1!
#172
0!
#173
1!
#174
0!
#175
1!
#176
0!
#177
1!
#178
0!
#179
0(
b110 ,
1.
1!
#180
0!
#181
0%
1!
#182
0!
#183
0/
1!
#184
0!
#185
1!
#186
0!
#187
1!
#188
0!
#189
1!
#190
0!
#191
1!
#192
0!
#193
1!
#194
0!
#195
0.
1!
#196
0!
#197
1!
#198
0!
#199
b110 -
1/
1!
#200
0!
#201
1!
#202
0!
#203
1!
#204
0!
#205
1!
#206
0!
#207
1!
#208
0!
#209
1!
#210
0!
#211
b111 ,
1(
1.
1!
#212
0!
#213
1%
1!
#214
0!
#215
0/
1!
#216
0!
#217
1!
#218
0!
#219
1!
#220
0!
#221
1!
#222
0!
#223
1!
#224
0!
#225
1!
#226
0!
#227
0.
1!
#228
0!
#229
1!
#230
0!
#231
b111 -
1/
1!
#232
0!
#233
1!
#234
0!
#235
1!
#236
0!
#237
1!
#238
0!
#239
1!
#240
0!
#241
1!
#242
0!
#243
0(
b1000 ,
1.
1!
#244
0!
#245
0%
1!
#246
0!
#247
0/
1!
#248
0!
#249
1!
#250
0!
#251
1!
#252
0!
#253
1!
#254
0!
#255
1!
#256
0!
#257
1!
#258
0!
#259
0.
1!
#260
0!
#261
1!
#262
0!
#263
b1000 -
1/
1!
#264
0!
#265
1!
#266
0!
#267
1!
#268
0!
#269
1!
#270
0!
#271
1!
#272
0!
#273
1!
#274
0!
#275
b1001 ,
1(
1.
1!
#276
0!
#277
1%
1!
#278
0!
#279
0/
1!
#280
0!
#281
1!
#282
0!
#283
1!
#284
0!
#285
1!
#286
0!
#287
1!
#288
0!
#289
1!
#290
0!
#291
0.
1!
#292
0!
#293
1!
#294
0!
#295
b1001 -
1/
1!
#296
0!
#297
1!
#298
0!
#299
1!
#300
0!
#301
1!
#302
0!
#303
1!
#304
0!
#305
1!
#306
0!
#307
1*
b0 ,
1.
1!
#308
0!
#309
1!
#310
0!
#311
0/
1!
#312
0!
#313
1!
#314
0!
#315
1!
#316
0!
#317
1!
#318
0!
#319
1!
#320
0!
#321
1!
#322
0!
#323
0.
1!
#324
0!
#325
1!
#326
0!
#327
b1010101 )
1+
b0 -
1/
1!
#328
0!
#329
0'
1!
#330
0!
#331
0/
0+
1!
#332
0!
#333
1!
#334
0!
#335
1!
#336
0!
#337
1!
#338
0!
#339
b1 ,
1.
1!
#340
0!
#341
1!
#342
0!
#343
1!
#344
0!
#345
1!
#346
0!
#347
1!
#348
0!
#349
1!
#350
0!
#351
1!
#352
0!
#353
1!
#354
0!
#355
0.
1!
#356
0!
#357
1!
#358
0!
0"
0&
#359
0*
b0 ,
1!
#360
0!
1"
b10101010 #
1&
#361
1!
#362
0!
#363
1!
#364
0!
#365
1!
#366
0!
#367
1!
#368
0!
#369
1!
#370
0!
#371
1!
#372
0!
#373
1!
#374
0!
#375
0(
b1 ,
1.
1!
#376
0!
#377
0%
1!
#378
0!
#379
1'
1!
#380
0!
#381
1!
#382
0!
#383
1!
#384
0!
#385
1!
#386
0!
#387
1!
#388
0!
#389
1!
#390
0!
#391
0.
1!
#392
0!
#393
1!
#394
0!
#395
b1 -
1/
1!
#396
0!
#397
1!
#398
0!
#399
1!
#400
0!
#401
1!
#402
0!
#403
1!
#404
0!
#405
1!
#406
0!
#407
b10 ,
1(
1.
1!
#408
0!
#409
1%
1!
#410
0!
#411
0/
1!
#412
0!
#413
1!
#414
0!
#415
1!
#416
0!
#417
1!
#418
0!
#419
1!
#420
0!
#421
1!
#422
0!
#423
0.
1!
#424
0!
#425
1!
#426
0!
#427
b10 -
1/
1!
#428
0!
#429
1!
#430
0!
#431
1!
#432
0!
#433
1!
#434
0!
#435
1!
#436
0!
#437
1!
#438
0!
#439
0(
b11 ,
1.
1!
#440
0!
#441
0%
1!
#442
0!
#443
0/
1!
#444
0!
#445
1!
#446
0!
#447
1!
#448
0!
#449
1!
#450
0!
#451
1!
#452
0!
#453
1!
#454
0!
#455
0.
1!
#456
0!
#457
1!
#458
0!
#459
b11 -
1/
1!
#460
0!
#461
1!
#462
0!
#463
1!
#464
0!
#465
1!
#466
0!
#467
1!
#468
0!
#469
1!
#470
0!
#471
b100 ,
1(
1.
1!
#472
0!
#473
1%
1!
#474
0!
#475
0/
1!
#476
0!
#477
1!
#478
0!
#479
1!
#480
0!
#481
1!
#482
0!
#483
1!
#484
0!
#485
1!
#486
0!
#487
0.
1!
#488
0!
#489
1!
#490
0!
#491
b100 -
1/
1!
#492
0!
#493
1!
#494
0!
#495
1!
#496
0!
#497
1!
#498
0!
#499
1!
#500
0!
#501
1!
#502
0!
#503
0(
b101 ,
1.
1!
#504
0!
#505
0%
1!
#506
0!
#507
0/
1!
#508
0!
#509
1!
#510
0!
#511
1!
#512
0!
#513
1!
#514
0!
#515
1!
#516
0!
#517
1!
#518
0!
#519
0.
1!
#520
0!
#521
1!
#522
0!
#523
b101 -
1/
1!
#524
0!
#525
1!
#526
0!
#527
1!
#528
0!
#529
1!
#530
0!
#531
1!
#532
0!
#533
1!
#534
0!
#535
b110 ,
1(
1.
1!
#536
0!
#537
1%
1!
#538
0!
#539
0/
1!
#540
0!
#541
1!
#542
0!
#543
1!
#544
0!
#545
1!
#546
0!
#547
1!
#548
0!
#549
1!
#550
0!
#551
0.
1!
#552
0!
#553
1!
#554
0!
#555
b110 -
1/
1!
#556
0!
#557
1!
#558
0!
#559
1!
#560
0!
#561
1!
#562
0!
#563
1!
#564
0!
#565
1!
#566
0!
#567
0(
b111 ,
1.
1!
#568
0!
#569
0%
1!
#570
0!
#571
0/
1!
#572
0!
#573
1!
#574
0!
#575
1!
#576
0!
#577
1!
#578
0!
#579
1!
#580
0!
#581
1!
#582
0!
#583
0.
1!
#584
0!
#585
1!
#586
0!
#587
b111 -
1/
1!
#588
0!
#589
1!
#590
0!
#591
1!
#592
0!
#593
1!
#594
0!
#595
1!
#596
0!
#597
1!
#598
0!
#599
b1000 ,
1(
1.
1!
#600
0!
#601
1%
1!
#602
0!
#603
0/
1!
#604
0!
#605
1!
#606
0!
#607
1!
#608
0!
#609
1!
#610
0!
#611
1!
#612
0!
#613
1!
#614
0!
#615
0.
1!
#616
0!
#617
1!
#618
0!
#619
b1000 -
1/
1!
#620
0!
#621
1!
#622
0!
#623
1!
#624
0!
#625
1!
#626
0!
#627
1!
#628
0!
#629
1!
#630
0!
#631
0(
b1001 ,
1.
1!
#632
0!
#633
0%
1!
#634
0!
#635
0/
1!
#636
0!
#637
1!
#638
0!
#639
1!
#640
0!
#641
1!
#642
0!
#643
1!
#644
0!
#645
1!
#646
0!
#647
0.
1!
#648
0!
#649
1!
#650
0!
#651
b1001 -
1/
1!
#652
0!
#653
1!
#654
0!
#655
1!
#656
0!
#657
1!
#658
0!
#659
1!
#660
0!
#661
1!
#662
0!
#663
1*
b0 ,
1(
1.
1!
#664
0!
#665
1%
1!
#666
0!
#667
0/
1!
#668
0!
#669
1!
#670
0!
#671
1!
#672
0!
#673
1!
#674
0!
#675
1!
#676
0!
#677
1!
#678
0!
#679
0.
1!
#680
0!
#681
1!
#682
0!
#683
b10101010 )
1+
b0 -
1/
1!
#684
0!
#685
0'
1!
#686
0!
#687
0/
0+
1!
#688
0!
#689
1!
#690
0!
#691
1!
#692
0!
#693
1!
#694
0!
#695
b1 ,
1.
1!
#696
0!
#697
1!
#698
0!
#699
1!
#700
0!
#701
1!
#702
0!
#703
1!
#704
0!
#705
1!
#706
0!
#707
1!
#708
0!
#709
1!
#710
0!
#711
0.
1!
#712
0!
#713
1!
#714
0!
0&
#715
0*
b0 ,
1!
