Lab4/startBitDetect.v
//module that identifies the start bit of a sent character. allows the counting
//circuits to begin running.
module startBitDetect(startBitDetected, characterReceived, data, clk, reset);
  output reg startBitDetected;
  input wire characterReceived, data, clk, reset;

  reg readingData;


  always@(posedge clk) begin
    if(reset) begin
      startBitDetected = 1'b0;
      readingData = 1'b0;
    end else begin
      startBitDetected <= readingData;
    end
  end

  always@(*) begin //readingData is a state machine that keeps track of whether the start bit has been detected
    case(readingData)
      1'b1: begin
        if(characterReceived) begin //only stop reading when the entirety of the character has been received
          readingData = 1'b0;
        end
      end
      1'b0: begin
        if(!data) begin //begin reading when receiving the start bit
          readingData = 1'b1;
        end
      end
      default: begin
        readingData = 1'b0;
      end
    endcase
  end
endmodule

module startBitDetect_testbench;
  wire startBitDetected;
  reg characterReceived, data, clk, reset;

  startBitDetect dut(startBitDetected, characterReceived, data, clk, reset);

  parameter ClockDelay = 2;
  initial begin //setup the clock
    clk <= 0;
    forever begin
      #(ClockDelay/2);
      clk <= ~clk;
    end
  end

  initial begin
    $dumpfile("startBitDetect.vcd");
    $dumpvars(1,dut);
    reset <= 1'b1;
    #ClockDelay;
    reset <= 1'b0;
    #ClockDelay;
    data = 1'b1;
    characterReceived = 1'b0;
    #ClockDelay;
    characterReceived = 1'b1;
    #ClockDelay;
    characterReceived = 1'b0;
    data = 1'b0;
    #ClockDelay;
    #ClockDelay;
    #ClockDelay;
    characterReceived = 1'b1;
    #ClockDelay;
    $finish;
  end
endmodule

Lab4/startBitDetect.vcd
$date
	Tue Feb 20 20:05:27 2018
$end
$version
	Icarus Verilog
$end
$timescale
	1s
$end
$scope module startBitDetect_testbench $end
$scope module dut $end
$var wire 1 ! characterReceived $end
$var wire 1 " clk $end
$var wire 1 # data $end
$var wire 1 $ reset $end
$var reg 1 % readingData $end
$var reg 1 & startBitDetected $end
$upscope $end
$upscope $end
$enddefinitions $end
#0
$dumpvars
x&
x%
1$
x#
0"
x!
$end
#1
0%
0&
1"
#2
0"
0$
#3
1"
#4
0"
0!
1#
#5
1"
#6
0"
1!
#7
1"
#8
0"
1%
0#
0!
#9
1&
1"
#10
0"
#11
1"
#12
0"
#13
1"
#14
0"
0%
1!
#15
0&
1"
