Lab3/sram.v
/*  This module implements SRAM based CY7C128A architecture
    that can hold approximately 16k bits (2k X 8) and has
    active low chip enable, active low write, and
    active low enable. */

module sram(data_out, data_in, addr, chipEnable, writeEnable, outputEnable);
  output reg  [7:0]   data_out;
  input wire  [7:0]   data_in;
  input wire  [10:0]  addr;
  input wire  chipEnable, writeEnable, outputEnable;

  /* 2048 X 8 RAM architecture */
  reg [7:0] mem [2047:0];

  always@(*) begin
    if (!chipEnable) begin
      if (!writeEnable) begin
        mem[addr] = data_in;
      end else if (!outputEnable) begin
        data_out = mem[addr];
      end
    end
  end

endmodule

/* Test writing to and reading from SRAM. */

module sram_testbench;
  wire  [7:0] data_out;
  reg   [7:0] data_in;
  reg   [10:0] addr;
  reg   chipEnable, writeEnable, outputEnable;

  sram sram_test(data_out, data_in, addr, chipEnable, writeEnable, outputEnable);
integer i;
  initial begin
    $dumpfile("sram.vcd");
    $dumpvars(1, sram_test);
    // Test 1: Should output all X's.
    chipEnable = 1'b0;
    writeEnable = 1'b0;
    outputEnable = 1'b1;
    for(i = 0; i < 2047; i++) begin
      addr = i;
      data_in = i % 255;
      #1;
    end
    writeEnable = 1'b1;
    outputEnable = 1'b0;
    for(i = 0; i < 2047; i++) begin
      addr = i;
      #1;
    end
  end

endmodule

Lab3/sram.vcd
$date
	Wed Feb 14 11:49:20 2018
$end
$version
	Icarus Verilog
$end
$timescale
	1s
$end
$scope module sram_testbench $end
$scope module sram_test $end
$var wire 11 ! addr [10:0] $end
$var wire 1 " chipEnable $end
$var wire 8 # data_in [7:0] $end
$var wire 1 $ outputEnable $end
$var wire 1 % writeEnable $end
$var reg 8 & data_out [7:0] $end
$upscope $end
$upscope $end
$enddefinitions $end
#0
$dumpvars
bx &
0%
1$
b0 #
0"
b0 !
$end
#1
b1 #
b1 !
#2
b10 #
b10 !
#3
b11 #
b11 !
#4
b100 #
b100 !
#5
b101 #
b101 !
#6
b110 #
b110 !
#7
b111 #
b111 !
#8
b1000 #
b1000 !
#9
b1001 #
b1001 !
#10
b1010 #
b1010 !
#11
b1011 #
b1011 !
#12
b1100 #
b1100 !
#13
b1101 #
b1101 !
#14
b1110 #
b1110 !
#15
b1111 #
b1111 !
#16
b10000 #
b10000 !
#17
b10001 #
b10001 !
#18
b10010 #
b10010 !
#19
b10011 #
b10011 !
#20
b10100 #
b10100 !
#21
b10101 #
b10101 !
#22
b10110 #
b10110 !
#23
b10111 #
b10111 !
#24
b11000 #
b11000 !
#25
b11001 #
b11001 !
#26
b11010 #
b11010 !
#27
b11011 #
b11011 !
#28
b11100 #
b11100 !
#29
b11101 #
b11101 !
#30
b11110 #
b11110 !
#31
b11111 #
b11111 !
#32
b100000 #
b100000 !
#33
b100001 #
b100001 !
#34
b100010 #
b100010 !
#35
b100011 #
b100011 !
#36
b100100 #
b100100 !
#37
b100101 #
b100101 !
#38
b100110 #
b100110 !
#39
b100111 #
b100111 !
#40
b101000 #
b101000 !
#41
b101001 #
b101001 !
#42
b101010 #
b101010 !
#43
b101011 #
b101011 !
#44
b101100 #
b101100 !
#45
b101101 #
b101101 !
#46
b101110 #
b101110 !
#47
b101111 #
b101111 !
#48
b110000 #
b110000 !
#49
b110001 #
b110001 !
#50
b110010 #
b110010 !
#51
b110011 #
b110011 !
#52
b110100 #
b110100 !
#53
b110101 #
b110101 !
#54
b110110 #
b110110 !
#55
b110111 #
b110111 !
#56
b111000 #
b111000 !
#57
b111001 #
b111001 !
#58
b111010 #
b111010 !
#59
b111011 #
b111011 !
#60
b111100 #
b111100 !
#61
b111101 #
b111101 !
#62
b111110 #
b111110 !
#63
b111111 #
b111111 !
#64
b1000000 #
b1000000 !
#65
b1000001 #
b1000001 !
#66
b1000010 #
b1000010 !
#67
b1000011 #
b1000011 !
#68
b1000100 #
b1000100 !
#69
b1000101 #
b1000101 !
#70
b1000110 #
b1000110 !
#71
b1000111 #
b1000111 !
#72
b1001000 #
b1001000 !
#73
b1001001 #
b1001001 !
#74
b1001010 #
b1001010 !
#75
b1001011 #
b1001011 !
#76
b1001100 #
b1001100 !
#77
b1001101 #
b1001101 !
#78
b1001110 #
b1001110 !
#79
b1001111 #
b1001111 !
#80
b1010000 #
b1010000 !
#81
b1010001 #
b1010001 !
#82
b1010010 #
b1010010 !
#83
b1010011 #
b1010011 !
#84
b1010100 #
b1010100 !
#85
b1010101 #
b1010101 !
#86
b1010110 #
b1010110 !
#87
b1010111 #
b1010111 !
#88
b1011000 #
b1011000 !
#89
b1011001 #
b1011001 !
#90
b1011010 #
b1011010 !
#91
b1011011 #
b1011011 !
#92
b1011100 #
b1011100 !
#93
b1011101 #
b1011101 !
#94
b1011110 #
b1011110 !
#95
b1011111 #
b1011111 !
#96
b1100000 #
b1100000 !
#97
b1100001 #
b1100001 !
#98
b1100010 #
b1100010 !
#99
b1100011 #
b1100011 !
#100
b1100100 #
b1100100 !
#101
b1100101 #
b1100101 !
#102
b1100110 #
b1100110 !
#103
b1100111 #
b1100111 !
#104
b1101000 #
b1101000 !
#105
b1101001 #
b1101001 !
#106
b1101010 #
b1101010 !
#107
b1101011 #
b1101011 !
#108
b1101100 #
b1101100 !
#109
b1101101 #
b1101101 !
#110
b1101110 #
b1101110 !
#111
b1101111 #
b1101111 !
#112
b1110000 #
b1110000 !
#113
b1110001 #
b1110001 !
#114
b1110010 #
b1110010 !
#115
b1110011 #
b1110011 !
#116
b1110100 #
b1110100 !
#117
b1110101 #
b1110101 !
#118
b1110110 #
b1110110 !
#119
b1110111 #
b1110111 !
#120
b1111000 #
b1111000 !
#121
b1111001 #
b1111001 !
#122
b1111010 #
b1111010 !
#123
b1111011 #
b1111011 !
#124
b1111100 #
b1111100 !
#125
b1111101 #
b1111101 !
#126
b1111110 #
b1111110 !
#127
b1111111 #
b1111111 !
#128
b10000000 #
b10000000 !
#129
b10000001 #
b10000001 !
#130
b10000010 #
b10000010 !
#131
b10000011 #
b10000011 !
#132
b10000100 #
b10000100 !
#133
b10000101 #
b10000101 !
#134
b10000110 #
b10000110 !
#135
b10000111 #
b10000111 !
#136
b10001000 #
b10001000 !
#137
b10001001 #
b10001001 !
#138
b10001010 #
b10001010 !
#139
b10001011 #
b10001011 !
#140
b10001100 #
b10001100 !
#141
b10001101 #
b10001101 !
#142
b10001110 #
b10001110 !
#143
b10001111 #
b10001111 !
#144
b10010000 #
b10010000 !
#145
b10010001 #
b10010001 !
#146
b10010010 #
b10010010 !
#147
b10010011 #
b10010011 !
#148
b10010100 #
b10010100 !
#149
b10010101 #
b10010101 !
#150
b10010110 #
b10010110 !
#151
b10010111 #
b10010111 !
#152
b10011000 #
b10011000 !
#153
b10011001 #
b10011001 !
#154
b10011010 #
b10011010 !
#155
b10011011 #
b10011011 !
#156
b10011100 #
b10011100 !
#157
b10011101 #
b10011101 !
#158
b10011110 #
b10011110 !
#159
b10011111 #
b10011111 !
#160
b10100000 #
b10100000 !
#161
b10100001 #
b10100001 !
#162
b10100010 #
b10100010 !
#163
b10100011 #
b10100011 !
#164
b10100100 #
b10100100 !
#165
b10100101 #
b10100101 !
#166
b10100110 #
b10100110 !
#167
b10100111 #
b10100111 !
#168
b10101000 #
b10101000 !
#169
b10101001 #
b10101001 !
#170
b10101010 #
b10101010 !
#171
b10101011 #
b10101011 !
#172
b10101100 #
b10101100 !
#173
b10101101 #
b10101101 !
#174
b10101110 #
b10101110 !
#175
b10101111 #
b10101111 !
#176
b10110000 #
b10110000 !
#177
b10110001 #
b10110001 !
#178
b10110010 #
b10110010 !
#179
b10110011 #
b10110011 !
#180
b10110100 #
b10110100 !
#181
b10110101 #
b10110101 !
#182
b10110110 #
b10110110 !
#183
b10110111 #
b10110111 !
#184
b10111000 #
b10111000 !
#185
b10111001 #
b10111001 !
#186
b10111010 #
b10111010 !
#187
b10111011 #
b10111011 !
#188
b10111100 #
b10111100 !
#189
b10111101 #
b10111101 !
#190
b10111110 #
b10111110 !
#191
b10111111 #
b10111111 !
#192
b11000000 #
b11000000 !
#193
b11000001 #
b11000001 !
#194
b11000010 #
b11000010 !
#195
b11000011 #
b11000011 !
#196
b11000100 #
b11000100 !
#197
b11000101 #
b11000101 !
#198
b11000110 #
b11000110 !
#199
b11000111 #
b11000111 !
#200
b11001000 #
b11001000 !
#201
b11001001 #
b11001001 !
#202
b11001010 #
b11001010 !
#203
b11001011 #
b11001011 !
#204
b11001100 #
b11001100 !
#205
b11001101 #
b11001101 !
#206
b11001110 #
b11001110 !
#207
b11001111 #
b11001111 !
#208
b11010000 #
b11010000 !
#209
b11010001 #
b11010001 !
#210
b11010010 #
b11010010 !
#211
b11010011 #
b11010011 !
#212
b11010100 #
b11010100 !
#213
b11010101 #
b11010101 !
#214
b11010110 #
b11010110 !
#215
b11010111 #
b11010111 !
#216
b11011000 #
b11011000 !
#217
b11011001 #
b11011001 !
#218
b11011010 #
b11011010 !
#219
b11011011 #
b11011011 !
#220
b11011100 #
b11011100 !
#221
b11011101 #
b11011101 !
#222
b11011110 #
b11011110 !
#223
b11011111 #
b11011111 !
#224
b11100000 #
b11100000 !
#225
b11100001 #
b11100001 !
#226
b11100010 #
b11100010 !
#227
b11100011 #
b11100011 !
#228
b11100100 #
b11100100 !
#229
b11100101 #
b11100101 !
#230
b11100110 #
b11100110 !
#231
b11100111 #
b11100111 !
#232
b11101000 #
b11101000 !
#233
b11101001 #
b11101001 !
#234
b11101010 #
b11101010 !
#235
b11101011 #
b11101011 !
#236
b11101100 #
b11101100 !
#237
b11101101 #
b11101101 !
#238
b11101110 #
b11101110 !
#239
b11101111 #
b11101111 !
#240
b11110000 #
b11110000 !
#241
b11110001 #
b11110001 !
#242
b11110010 #
b11110010 !
#243
b11110011 #
b11110011 !
#244
b11110100 #
b11110100 !
#245
b11110101 #
b11110101 !
#246
b11110110 #
b11110110 !
#247
b11110111 #
b11110111 !
#248
b11111000 #
b11111000 !
#249
b11111001 #
b11111001 !
#250
b11111010 #
b11111010 !
#251
b11111011 #
b11111011 !
#252
b11111100 #
b11111100 !
#253
b11111101 #
b11111101 !
#254
b11111110 #
b11111110 !
#255
b0 #
b11111111 !
#256
b1 #
b100000000 !
#257
b10 #
b100000001 !
#258
b11 #
b100000010 !
#259
b100 #
b100000011 !
#260
b101 #
b100000100 !
#261
b110 #
b100000101 !
#262
b111 #
b100000110 !
#263
b1000 #
b100000111 !
#264
b1001 #
b100001000 !
#265
b1010 #
b100001001 !
#266
b1011 #
b100001010 !
#267
b1100 #
b100001011 !
#268
b1101 #
b100001100 !
#269
b1110 #
b100001101 !
#270
b1111 #
b100001110 !
#271
b10000 #
b100001111 !
#272
b10001 #
b100010000 !
#273
b10010 #
b100010001 !
#274
b10011 #
b100010010 !
#275
b10100 #
b100010011 !
#276
b10101 #
b100010100 !
#277
b10110 #
b100010101 !
#278
b10111 #
b100010110 !
#279
b11000 #
b100010111 !
#280
b11001 #
b100011000 !
#281
b11010 #
b100011001 !
#282
b11011 #
b100011010 !
#283
b11100 #
b100011011 !
#284
b11101 #
b100011100 !
#285
b11110 #
b100011101 !
#286
b11111 #
b100011110 !
#287
b100000 #
b100011111 !
#288
b100001 #
b100100000 !
#289
b100010 #
b100100001 !
#290
b100011 #
b100100010 !
#291
b100100 #
b100100011 !
#292
b100101 #
b100100100 !
#293
b100110 #
b100100101 !
#294
b100111 #
b100100110 !
#295
b101000 #
b100100111 !
#296
b101001 #
b100101000 !
#297
b101010 #
b100101001 !
#298
b101011 #
b100101010 !
#299
b101100 #
b100101011 !
#300
b101101 #
b100101100 !
#301
b101110 #
b100101101 !
#302
b101111 #
b100101110 !
#303
b110000 #
b100101111 !
#304
b110001 #
b100110000 !
#305
b110010 #
b100110001 !
#306
b110011 #
b100110010 !
#307
b110100 #
b100110011 !
#308
b110101 #
b100110100 !
#309
b110110 #
b100110101 !
#310
b110111 #
b100110110 !
#311
b111000 #
b100110111 !
#312
b111001 #
b100111000 !
#313
b111010 #
b100111001 !
#314
b111011 #
b100111010 !
#315
b111100 #
b100111011 !
#316
b111101 #
b100111100 !
#317
b111110 #
b100111101 !
#318
b111111 #
b100111110 !
#319
b1000000 #
b100111111 !
#320
b1000001 #
b101000000 !
#321
b1000010 #
b101000001 !
#322
b1000011 #
b101000010 !
#323
b1000100 #
b101000011 !
#324
b1000101 #
b101000100 !
#325
b1000110 #
b101000101 !
#326
b1000111 #
b101000110 !
#327
b1001000 #
b101000111 !
#328
b1001001 #
b101001000 !
#329
b1001010 #
b101001001 !
#330
b1001011 #
b101001010 !
#331
b1001100 #
b101001011 !
#332
b1001101 #
b101001100 !
#333
b1001110 #
b101001101 !
#334
b1001111 #
b101001110 !
#335
b1010000 #
b101001111 !
#336
b1010001 #
b101010000 !
#337
b1010010 #
b101010001 !
#338
b1010011 #
b101010010 !
#339
b1010100 #
b101010011 !
#340
b1010101 #
b101010100 !
#341
b1010110 #
b101010101 !
#342
b1010111 #
b101010110 !
#343
b1011000 #
b101010111 !
#344
b1011001 #
b101011000 !
#345
b1011010 #
b101011001 !
#346
b1011011 #
b101011010 !
#347
b1011100 #
b101011011 !
#348
b1011101 #
b101011100 !
#349
b1011110 #
b101011101 !
#350
b1011111 #
b101011110 !
#351
b1100000 #
b101011111 !
#352
b1100001 #
b101100000 !
#353
b1100010 #
b101100001 !
#354
b1100011 #
b101100010 !
#355
b1100100 #
b101100011 !
#356
b1100101 #
b101100100 !
#357
b1100110 #
b101100101 !
#358
b1100111 #
b101100110 !
#359
b1101000 #
b101100111 !
#360
b1101001 #
b101101000 !
#361
b1101010 #
b101101001 !
#362
b1101011 #
b101101010 !
#363
b1101100 #
b101101011 !
#364
b1101101 #
b101101100 !
#365
b1101110 #
b101101101 !
#366
b1101111 #
b101101110 !
#367
b1110000 #
b101101111 !
#368
b1110001 #
b101110000 !
#369
b1110010 #
b101110001 !
#370
b1110011 #
b101110010 !
#371
b1110100 #
b101110011 !
#372
b1110101 #
b101110100 !
#373
b1110110 #
b101110101 !
#374
b1110111 #
b101110110 !
#375
b1111000 #
b101110111 !
#376
b1111001 #
b101111000 !
#377
b1111010 #
b101111001 !
#378
b1111011 #
b101111010 !
#379
b1111100 #
b101111011 !
#380
b1111101 #
b101111100 !
#381
b1111110 #
b101111101 !
#382
b1111111 #
b101111110 !
#383
b10000000 #
b101111111 !
#384
b10000001 #
b110000000 !
#385
b10000010 #
b110000001 !
#386
b10000011 #
b110000010 !
#387
b10000100 #
b110000011 !
#388
b10000101 #
b110000100 !
#389
b10000110 #
b110000101 !
#390
b10000111 #
b110000110 !
#391
b10001000 #
b110000111 !
#392
b10001001 #
b110001000 !
#393
b10001010 #
b110001001 !
#394
b10001011 #
b110001010 !
#395
b10001100 #
b110001011 !
#396
b10001101 #
b110001100 !
#397
b10001110 #
b110001101 !
#398
b10001111 #
b110001110 !
#399
b10010000 #
b110001111 !
#400
b10010001 #
b110010000 !
#401
b10010010 #
b110010001 !
#402
b10010011 #
b110010010 !
#403
b10010100 #
b110010011 !
#404
b10010101 #
b110010100 !
#405
b10010110 #
b110010101 !
#406
b10010111 #
b110010110 !
#407
b10011000 #
b110010111 !
#408
b10011001 #
b110011000 !
#409
b10011010 #
b110011001 !
#410
b10011011 #
b110011010 !
#411
b10011100 #
b110011011 !
#412
b10011101 #
b110011100 !
#413
b10011110 #
b110011101 !
#414
b10011111 #
b110011110 !
#415
b10100000 #
b110011111 !
#416
b10100001 #
b110100000 !
#417
b10100010 #
b110100001 !
#418
b10100011 #
b110100010 !
#419
b10100100 #
b110100011 !
#420
b10100101 #
b110100100 !
#421
b10100110 #
b110100101 !
#422
b10100111 #
b110100110 !
#423
b10101000 #
b110100111 !
#424
b10101001 #
b110101000 !
#425
b10101010 #
b110101001 !
#426
b10101011 #
b110101010 !
#427
b10101100 #
b110101011 !
#428
b10101101 #
b110101100 !
#429
b10101110 #
b110101101 !
#430
b10101111 #
b110101110 !
#431
b10110000 #
b110101111 !
#432
b10110001 #
b110110000 !
#433
b10110010 #
b110110001 !
#434
b10110011 #
b110110010 !
#435
b10110100 #
b110110011 !
#436
b10110101 #
b110110100 !
#437
b10110110 #
b110110101 !
#438
b10110111 #
b110110110 !
#439
b10111000 #
b110110111 !
#440
b10111001 #
b110111000 !
#441
b10111010 #
b110111001 !
#442
b10111011 #
b110111010 !
#443
b10111100 #
b110111011 !
#444
b10111101 #
b110111100 !
#445
b10111110 #
b110111101 !
#446
b10111111 #
b110111110 !
#447
b11000000 #
b110111111 !
#448
b11000001 #
b111000000 !
#449
b11000010 #
b111000001 !
#450
b11000011 #
b111000010 !
#451
b11000100 #
b111000011 !
#452
b11000101 #
b111000100 !
#453
b11000110 #
b111000101 !
#454
b11000111 #
b111000110 !
#455
b11001000 #
b111000111 !
#456
b11001001 #
b111001000 !
#457
b11001010 #
b111001001 !
#458
b11001011 #
b111001010 !
#459
b11001100 #
b111001011 !
#460
b11001101 #
b111001100 !
#461
b11001110 #
b111001101 !
#462
b11001111 #
b111001110 !
#463
b11010000 #
b111001111 !
#464
b11010001 #
b111010000 !
#465
b11010010 #
b111010001 !
#466
b11010011 #
b111010010 !
#467
b11010100 #
b111010011 !
#468
b11010101 #
b111010100 !
#469
b11010110 #
b111010101 !
#470
b11010111 #
b111010110 !
#471
b11011000 #
b111010111 !
#472
b11011001 #
b111011000 !
#473
b11011010 #
b111011001 !
#474
b11011011 #
b111011010 !
#475
b11011100 #
b111011011 !
#476
b11011101 #
b111011100 !
#477
b11011110 #
b111011101 !
#478
b11011111 #
b111011110 !
#479
b11100000 #
b111011111 !
#480
b11100001 #
b111100000 !
#481
b11100010 #
b111100001 !
#482
b11100011 #
b111100010 !
#483
b11100100 #
b111100011 !
#484
b11100101 #
b111100100 !
#485
b11100110 #
b111100101 !
#486
b11100111 #
b111100110 !
#487
b11101000 #
b111100111 !
#488
b11101001 #
b111101000 !
#489
b11101010 #
b111101001 !
#490
b11101011 #
b111101010 !
#491
b11101100 #
b111101011 !
#492
b11101101 #
b111101100 !
#493
b11101110 #
b111101101 !
#494
b11101111 #
b111101110 !
#495
b11110000 #
b111101111 !
#496
b11110001 #
b111110000 !
#497
b11110010 #
b111110001 !
#498
b11110011 #
b111110010 !
#499
b11110100 #
b111110011 !
#500
b11110101 #
b111110100 !
#501
b11110110 #
b111110101 !
#502
b11110111 #
b111110110 !
#503
b11111000 #
b111110111 !
#504
b11111001 #
b111111000 !
#505
b11111010 #
b111111001 !
#506
b11111011 #
b111111010 !
#507
b11111100 #
b111111011 !
#508
b11111101 #
b111111100 !
#509
b11111110 #
b111111101 !
#510
b0 #
b111111110 !
#511
b1 #
b111111111 !
#512
b10 #
b1000000000 !
#513
b11 #
b1000000001 !
#514
b100 #
b1000000010 !
#515
b101 #
b1000000011 !
#516
b110 #
b1000000100 !
#517
b111 #
b1000000101 !
#518
b1000 #
b1000000110 !
#519
b1001 #
b1000000111 !
#520
b1010 #
b1000001000 !
#521
b1011 #
b1000001001 !
#522
b1100 #
b1000001010 !
#523
b1101 #
b1000001011 !
#524
b1110 #
b1000001100 !
#525
b1111 #
b1000001101 !
#526
b10000 #
b1000001110 !
#527
b10001 #
b1000001111 !
#528
b10010 #
b1000010000 !
#529
b10011 #
b1000010001 !
#530
b10100 #
b1000010010 !
#531
b10101 #
b1000010011 !
#532
b10110 #
b1000010100 !
#533
b10111 #
b1000010101 !
#534
b11000 #
b1000010110 !
#535
b11001 #
b1000010111 !
#536
b11010 #
b1000011000 !
#537
b11011 #
b1000011001 !
#538
b11100 #
b1000011010 !
#539
b11101 #
b1000011011 !
#540
b11110 #
b1000011100 !
#541
b11111 #
b1000011101 !
#542
b100000 #
b1000011110 !
#543
b100001 #
b1000011111 !
#544
b100010 #
b1000100000 !
#545
b100011 #
b1000100001 !
#546
b100100 #
b1000100010 !
#547
b100101 #
b1000100011 !
#548
b100110 #
b1000100100 !
#549
b100111 #
b1000100101 !
#550
b101000 #
b1000100110 !
#551
b101001 #
b1000100111 !
#552
b101010 #
b1000101000 !
#553
b101011 #
b1000101001 !
#554
b101100 #
b1000101010 !
#555
b101101 #
b1000101011 !
#556
b101110 #
b1000101100 !
#557
b101111 #
b1000101101 !
#558
b110000 #
b1000101110 !
#559
b110001 #
b1000101111 !
#560
b110010 #
b1000110000 !
#561
b110011 #
b1000110001 !
#562
b110100 #
b1000110010 !
#563
b110101 #
b1000110011 !
#564
b110110 #
b1000110100 !
#565
b110111 #
b1000110101 !
#566
b111000 #
b1000110110 !
#567
b111001 #
b1000110111 !
#568
b111010 #
b1000111000 !
#569
b111011 #
b1000111001 !
#570
b111100 #
b1000111010 !
#571
b111101 #
b1000111011 !
#572
b111110 #
b1000111100 !
#573
b111111 #
b1000111101 !
#574
b1000000 #
b1000111110 !
#575
b1000001 #
b1000111111 !
#576
b1000010 #
b1001000000 !
#577
b1000011 #
b1001000001 !
#578
b1000100 #
b1001000010 !
#579
b1000101 #
b1001000011 !
#580
b1000110 #
b1001000100 !
#581
b1000111 #
b1001000101 !
#582
b1001000 #
b1001000110 !
#583
b1001001 #
b1001000111 !
#584
b1001010 #
b1001001000 !
#585
b1001011 #
b1001001001 !
#586
b1001100 #
b1001001010 !
#587
b1001101 #
b1001001011 !
#588
b1001110 #
b1001001100 !
#589
b1001111 #
b1001001101 !
#590
b1010000 #
b1001001110 !
#591
b1010001 #
b1001001111 !
#592
b1010010 #
b1001010000 !
#593
b1010011 #
b1001010001 !
#594
b1010100 #
b1001010010 !
#595
b1010101 #
b1001010011 !
#596
b1010110 #
b1001010100 !
#597
b1010111 #
b1001010101 !
#598
b1011000 #
b1001010110 !
#599
b1011001 #
b1001010111 !
#600
b1011010 #
b1001011000 !
#601
b1011011 #
b1001011001 !
#602
b1011100 #
b1001011010 !
#603
b1011101 #
b1001011011 !
#604
b1011110 #
b1001011100 !
#605
b1011111 #
b1001011101 !
#606
b1100000 #
b1001011110 !
#607
b1100001 #
b1001011111 !
#608
b1100010 #
b1001100000 !
#609
b1100011 #
b1001100001 !
#610
b1100100 #
b1001100010 !
#611
b1100101 #
b1001100011 !
#612
b1100110 #
b1001100100 !
#613
b1100111 #
b1001100101 !
#614
b1101000 #
b1001100110 !
#615
b1101001 #
b1001100111 !
#616
b1101010 #
b1001101000 !
#617
b1101011 #
b1001101001 !
#618
b1101100 #
b1001101010 !
#619
b1101101 #
b1001101011 !
#620
b1101110 #
b1001101100 !
#621
b1101111 #
b1001101101 !
#622
b1110000 #
b1001101110 !
#623
b1110001 #
b1001101111 !
#624
b1110010 #
b1001110000 !
#625
b1110011 #
b1001110001 !
#626
b1110100 #
b1001110010 !
#627
b1110101 #
b1001110011 !
#628
b1110110 #
b1001110100 !
#629
b1110111 #
b1001110101 !
#630
b1111000 #
b1001110110 !
#631
b1111001 #
b1001110111 !
#632
b1111010 #
b1001111000 !
#633
b1111011 #
b1001111001 !
#634
b1111100 #
b1001111010 !
#635
b1111101 #
b1001111011 !
#636
b1111110 #
b1001111100 !
#637
b1111111 #
b1001111101 !
#638
b10000000 #
b1001111110 !
#639
b10000001 #
b1001111111 !
#640
b10000010 #
b1010000000 !
#641
b10000011 #
b1010000001 !
#642
b10000100 #
b1010000010 !
#643
b10000101 #
b1010000011 !
#644
b10000110 #
b1010000100 !
#645
b10000111 #
b1010000101 !
#646
b10001000 #
b1010000110 !
#647
b10001001 #
b1010000111 !
#648
b10001010 #
b1010001000 !
#649
b10001011 #
b1010001001 !
#650
b10001100 #
b1010001010 !
#651
b10001101 #
b1010001011 !
#652
b10001110 #
b1010001100 !
#653
b10001111 #
b1010001101 !
#654
b10010000 #
b1010001110 !
#655
b10010001 #
b1010001111 !
#656
b10010010 #
b1010010000 !
#657
b10010011 #
b1010010001 !
#658
b10010100 #
b1010010010 !
#659
b10010101 #
b1010010011 !
#660
b10010110 #
b1010010100 !
#661
b10010111 #
b1010010101 !
#662
b10011000 #
b1010010110 !
#663
b10011001 #
b1010010111 !
#664
b10011010 #
b1010011000 !
#665
b10011011 #
b1010011001 !
#666
b10011100 #
b1010011010 !
#667
b10011101 #
b1010011011 !
#668
b10011110 #
b1010011100 !
#669
b10011111 #
b1010011101 !
#670
b10100000 #
b1010011110 !
#671
b10100001 #
b1010011111 !
#672
b10100010 #
b1010100000 !
#673
b10100011 #
b1010100001 !
#674
b10100100 #
b1010100010 !
#675
b10100101 #
b1010100011 !
#676
b10100110 #
b1010100100 !
#677
b10100111 #
b1010100101 !
#678
b10101000 #
b1010100110 !
#679
b10101001 #
b1010100111 !
#680
b10101010 #
b1010101000 !
#681
b10101011 #
b1010101001 !
#682
b10101100 #
b1010101010 !
#683
b10101101 #
b1010101011 !
#684
b10101110 #
b1010101100 !
#685
b10101111 #
b1010101101 !
#686
b10110000 #
b1010101110 !
#687
b10110001 #
b1010101111 !
#688
b10110010 #
b1010110000 !
#689
b10110011 #
b1010110001 !
#690
b10110100 #
b1010110010 !
#691
b10110101 #
b1010110011 !
#692
b10110110 #
b1010110100 !
#693
b10110111 #
b1010110101 !
#694
b10111000 #
b1010110110 !
#695
b10111001 #
b1010110111 !
#696
b10111010 #
b1010111000 !
#697
b10111011 #
b1010111001 !
#698
b10111100 #
b1010111010 !
#699
b10111101 #
b1010111011 !
#700
b10111110 #
b1010111100 !
#701
b10111111 #
b1010111101 !
#702
b11000000 #
b1010111110 !
#703
b11000001 #
b1010111111 !
#704
b11000010 #
b1011000000 !
#705
b11000011 #
b1011000001 !
#706
b11000100 #
b1011000010 !
#707
b11000101 #
b1011000011 !
#708
b11000110 #
b1011000100 !
#709
b11000111 #
b1011000101 !
#710
b11001000 #
b1011000110 !
#711
b11001001 #
b1011000111 !
#712
b11001010 #
b1011001000 !
#713
b11001011 #
b1011001001 !
#714
b11001100 #
b1011001010 !
#715
b11001101 #
b1011001011 !
#716
b11001110 #
b1011001100 !
#717
b11001111 #
b1011001101 !
#718
b11010000 #
b1011001110 !
#719
b11010001 #
b1011001111 !
#720
b11010010 #
b1011010000 !
#721
b11010011 #
b1011010001 !
#722
b11010100 #
b1011010010 !
#723
b11010101 #
b1011010011 !
#724
b11010110 #
b1011010100 !
#725
b11010111 #
b1011010101 !
#726
b11011000 #
b1011010110 !
#727
b11011001 #
b1011010111 !
#728
b11011010 #
b1011011000 !
#729
b11011011 #
b1011011001 !
#730
b11011100 #
b1011011010 !
#731
b11011101 #
b1011011011 !
#732
b11011110 #
b1011011100 !
#733
b11011111 #
b1011011101 !
#734
b11100000 #
b1011011110 !
#735
b11100001 #
b1011011111 !
#736
b11100010 #
b1011100000 !
#737
b11100011 #
b1011100001 !
#738
b11100100 #
b1011100010 !
#739
b11100101 #
b1011100011 !
#740
b11100110 #
b1011100100 !
#741
b11100111 #
b1011100101 !
#742
b11101000 #
b1011100110 !
#743
b11101001 #
b1011100111 !
#744
b11101010 #
b1011101000 !
#745
b11101011 #
b1011101001 !
#746
b11101100 #
b1011101010 !
#747
b11101101 #
b1011101011 !
#748
b11101110 #
b1011101100 !
#749
b11101111 #
b1011101101 !
#750
b11110000 #
b1011101110 !
#751
b11110001 #
b1011101111 !
#752
b11110010 #
b1011110000 !
#753
b11110011 #
b1011110001 !
#754
b11110100 #
b1011110010 !
#755
b11110101 #
b1011110011 !
#756
b11110110 #
b1011110100 !
#757
b11110111 #
b1011110101 !
#758
b11111000 #
b1011110110 !
#759
b11111001 #
b1011110111 !
#760
b11111010 #
b1011111000 !
#761
b11111011 #
b1011111001 !
#762
b11111100 #
b1011111010 !
#763
b11111101 #
b1011111011 !
#764
b11111110 #
b1011111100 !
#765
b0 #
b1011111101 !
#766
b1 #
b1011111110 !
#767
b10 #
b1011111111 !
#768
b11 #
b1100000000 !
#769
b100 #
b1100000001 !
#770
b101 #
b1100000010 !
#771
b110 #
b1100000011 !
#772
b111 #
b1100000100 !
#773
b1000 #
b1100000101 !
#774
b1001 #
b1100000110 !
#775
b1010 #
b1100000111 !
#776
b1011 #
b1100001000 !
#777
b1100 #
b1100001001 !
#778
b1101 #
b1100001010 !
#779
b1110 #
b1100001011 !
#780
b1111 #
b1100001100 !
#781
b10000 #
b1100001101 !
#782
b10001 #
b1100001110 !
#783
b10010 #
b1100001111 !
#784
b10011 #
b1100010000 !
#785
b10100 #
b1100010001 !
#786
b10101 #
b1100010010 !
#787
b10110 #
b1100010011 !
#788
b10111 #
b1100010100 !
#789
b11000 #
b1100010101 !
#790
b11001 #
b1100010110 !
#791
b11010 #
b1100010111 !
#792
b11011 #
b1100011000 !
#793
b11100 #
b1100011001 !
#794
b11101 #
b1100011010 !
#795
b11110 #
b1100011011 !
#796
b11111 #
b1100011100 !
#797
b100000 #
b1100011101 !
#798
b100001 #
b1100011110 !
#799
b100010 #
b1100011111 !
#800
b100011 #
b1100100000 !
#801
b100100 #
b1100100001 !
#802
b100101 #
b1100100010 !
#803
b100110 #
b1100100011 !
#804
b100111 #
b1100100100 !
#805
b101000 #
b1100100101 !
#806
b101001 #
b1100100110 !
#807
b101010 #
b1100100111 !
#808
b101011 #
b1100101000 !
#809
b101100 #
b1100101001 !
#810
b101101 #
b1100101010 !
#811
b101110 #
b1100101011 !
#812
b101111 #
b1100101100 !
#813
b110000 #
b1100101101 !
#814
b110001 #
b1100101110 !
#815
b110010 #
b1100101111 !
#816
b110011 #
b1100110000 !
#817
b110100 #
b1100110001 !
#818
b110101 #
b1100110010 !
#819
b110110 #
b1100110011 !
#820
b110111 #
b1100110100 !
#821
b111000 #
b1100110101 !
#822
b111001 #
b1100110110 !
#823
b111010 #
b1100110111 !
#824
b111011 #
b1100111000 !
#825
b111100 #
b1100111001 !
#826
b111101 #
b1100111010 !
#827
b111110 #
b1100111011 !
#828
b111111 #
b1100111100 !
#829
b1000000 #
b1100111101 !
#830
b1000001 #
b1100111110 !
#831
b1000010 #
b1100111111 !
